{
  "players": {
    "P9484": {
      "g": 31,
      "gs": 31,
      "pa": 116,
      "ab": 106,
      "r": 17,
      "h": 25,
      "b1": 17,
      "b2": 4,
      "b3": 2,
      "hr": 2,
      "rbi": 9,
      "bb": 9,
      "ibb": 0,
      "hbp": 1,
      "so": 27,
      "so_looking": 5,
      "so_swinging": 22,
      "sh": 0,
      "sf": 0,
      "roe": 0,
      "fc": 1,
      "ci": 0,
      "gidp": 0,
      "sb": 7,
      "cs": 0,
      "po": 70,
      "pocs": 0,
      "pitches": 443,
      "lob": 17,
      "lead": 268,
      "gb": 31,
      "ld": 16,
      "fb": 31,
      "tb": 39,
      "xbh": 8,
      "p_pa": 3.8189655172413794,
      "avg": 0.2358490566037736,
      "obp": 0.3017241379310345,
      "slg": 0.36792452830188677,
      "ops": 0.6696486662329213,
      "iso": 0.13207547169811318,
      "babip": 0.2987012987012987,
      "bb_pct": 0.07758620689655173,
      "k_pct": 0.23275862068965517,
      "bb_k": 0.3333333333333333,
      "so_looking_pct": 0.18518518518518517,
      "sb_pct": 1.0,
      "gb_pct": 0.3974358974358974,
      "ld_pct": 0.20512820512820512,
      "fb_pct": 0.3974358974358974,
      "gb_fb": 1.0,
      "ld_fb_ratio": 0.5161290322580645,
      "2b": 4,
      "3b": 2,
      "a": 0,
      "e": 1,
      "dp": 0,
      "tp": 0,
      "pk": 0,
      "pb": 0,
      "sba": 0,
      "tc": 71,
      "of_a": 0,
      "fpct": 0.9859154929577465,
      "rf9": 2.2580645161290325,
      "rfg": 2.2580645161290325,
      "cs_pct": 0.0,
      "pb_g": 0.0
    },
    "P3557": {
      "g": 31,
      "gs": 31,
      "pa": 141,
      "ab": 126,
      "r": 12,
      "h": 28,
      "b1": 15,
      "b2": 10,
      "b3": 0,
      "hr": 3,
      "rbi": 12,
      "bb": 11,
      "ibb": 0,
      "hbp": 0,
      "so": 21,
      "so_looking": 7,
      "so_swinging": 14,
      "sh": 1,
      "sf": 2,
      "roe": 0,
      "fc": 0,
      "ci": 1,
      "gidp": 3,
      "sb": 8,
      "cs": 1,
      "po": 279,
      "pocs": 0,
      "pitches": 473,
      "lob": 20,
      "lead": 15,
      "gb": 48,
      "ld": 21,
      "fb": 37,
      "tb": 47,
      "xbh": 13,
      "p_pa": 3.354609929078014,
      "avg": 0.2222222222222222,
      "obp": 0.2805755395683453,
      "slg": 0.373015873015873,
      "ops": 0.6535914125842184,
      "iso": 0.1507936507936508,
      "babip": 0.2403846153846154,
      "bb_pct": 0.07801418439716312,
      "k_pct": 0.14893617021276595,
      "bb_k": 0.5238095238095238,
      "so_looking_pct": 0.3333333333333333,
      "sb_pct": 0.8888888888888888,
      "gb_pct": 0.4528301886792453,
      "ld_pct": 0.19811320754716982,
      "fb_pct": 0.3490566037735849,
      "gb_fb": 1.2972972972972974,
      "ld_fb_ratio": 0.5675675675675675,
      "2b": 10,
      "3b": 0,
      "a": 0,
      "e": 0,
      "dp": 16,
      "tp": 0,
      "pk": 0,
      "pb": 0,
      "sba": 0,
      "tc": 279,
      "of_a": 0,
      "fpct": 1.0,
      "rf9": 9.0,
      "rfg": 9.0,
      "cs_pct": 0.0,
      "pb_g": 0.0
    },
    "P3330": {
      "g": 31,
      "gs": 31,
      "pa": 139,
      "ab": 124,
      "r": 9,
      "h": 22,
      "b1": 14,
      "b2": 5,
      "b3": 0,
      "hr": 3,
      "rbi": 13,
      "bb": 11,
      "ibb": 0,
      "hbp": 1,
      "so": 33,
      "so_looking": 8,
      "so_swinging": 25,
      "sh": 0,
      "sf": 3,
      "roe": 2,
      "fc": 1,
      "ci": 0,
      "gidp": 3,
      "sb": 2,
      "cs": 1,
      "po": 32,
      "pocs": 0,
      "pitches": 541,
      "lob": 25,
      "lead": 7,
      "gb": 33,
      "ld": 21,
      "fb": 40,
      "tb": 36,
      "xbh": 8,
      "p_pa": 3.8920863309352516,
      "avg": 0.1774193548387097,
      "obp": 0.2446043165467626,
      "slg": 0.2903225806451613,
      "ops": 0.5349268971919239,
      "iso": 0.11290322580645162,
      "babip": 0.2087912087912088,
      "bb_pct": 0.07913669064748201,
      "k_pct": 0.23741007194244604,
      "bb_k": 0.3333333333333333,
      "so_looking_pct": 0.24242424242424243,
      "sb_pct": 0.6666666666666666,
      "gb_pct": 0.35106382978723405,
      "ld_pct": 0.22340425531914893,
      "fb_pct": 0.425531914893617,
      "gb_fb": 0.825,
      "ld_fb_ratio": 0.525,
      "2b": 5,
      "3b": 0,
      "a": 117,
      "e": 4,
      "dp": 10,
      "tp": 0,
      "pk": 0,
      "pb": 0,
      "sba": 0,
      "tc": 153,
      "of_a": 0,
      "fpct": 0.9738562091503268,
      "rf9": 4.806451612903226,
      "rfg": 4.806451612903226,
      "cs_pct": 0.0,
      "pb_g": 0.0
    },
    "P1213": {
      "g": 31,
      "gs": 31,
      "pa": 132,
      "ab": 113,
      "r": 12,
      "h": 33,
      "b1": 23,
      "b2": 7,
      "b3": 0,
      "hr": 3,
      "rbi": 13,
      "bb": 14,
      "ibb": 0,
      "hbp": 2,
      "so": 26,
      "so_looking": 3,
      "so_swinging": 23,
      "sh": 0,
      "sf": 2,
      "roe": 0,
      "fc": 1,
      "ci": 0,
      "gidp": 1,
      "sb": 3,
      "cs": 3,
      "po": 0,
      "pocs": 0,
      "pitches": 499,
      "lob": 28,
      "lead": 15,
      "gb": 33,
      "ld": 24,
      "fb": 32,
      "tb": 49,
      "xbh": 10,
      "p_pa": 3.7803030303030303,
      "avg": 0.2920353982300885,
      "obp": 0.37404580152671757,
      "slg": 0.4336283185840708,
      "ops": 0.8076741201107884,
      "iso": 0.1415929203539823,
      "babip": 0.3488372093023256,
      "bb_pct": 0.10606060606060606,
      "k_pct": 0.19696969696969696,
      "bb_k": 0.5384615384615384,
      "so_looking_pct": 0.11538461538461539,
      "sb_pct": 0.5,
      "gb_pct": 0.3707865168539326,
      "ld_pct": 0.2696629213483146,
      "fb_pct": 0.3595505617977528,
      "gb_fb": 1.03125,
      "ld_fb_ratio": 0.75,
      "2b": 7,
      "3b": 0
    },
    "P1624": {
      "g": 31,
      "gs": 31,
      "pa": 130,
      "ab": 115,
      "r": 14,
      "h": 35,
      "b1": 23,
      "b2": 3,
      "b3": 0,
      "hr": 9,
      "rbi": 21,
      "bb": 13,
      "ibb": 0,
      "hbp": 2,
      "so": 22,
      "so_looking": 7,
      "so_swinging": 15,
      "sh": 0,
      "sf": 0,
      "roe": 2,
      "fc": 2,
      "ci": 3,
      "gidp": 3,
      "sb": 1,
      "cs": 8,
      "po": 278,
      "pocs": 0,
      "pitches": 513,
      "lob": 31,
      "lead": 10,
      "gb": 34,
      "ld": 25,
      "fb": 34,
      "tb": 65,
      "xbh": 12,
      "p_pa": 3.9461538461538463,
      "avg": 0.30434782608695654,
      "obp": 0.38461538461538464,
      "slg": 0.5652173913043478,
      "ops": 0.9498327759197325,
      "iso": 0.26086956521739124,
      "babip": 0.30952380952380953,
      "bb_pct": 0.1,
      "k_pct": 0.16923076923076924,
      "bb_k": 0.5909090909090909,
      "so_looking_pct": 0.3181818181818182,
      "sb_pct": 0.1111111111111111,
      "gb_pct": 0.3655913978494624,
      "ld_pct": 0.26881720430107525,
      "fb_pct": 0.3655913978494624,
      "gb_fb": 1.0,
      "ld_fb_ratio": 0.7352941176470589,
      "2b": 3,
      "3b": 0,
      "a": 6,
      "e": 0,
      "dp": 0,
      "tp": 0,
      "pk": 0,
      "pb": 7,
      "sba": 52,
      "tc": 284,
      "of_a": 0,
      "fpct": 1.0,
      "rf9": 9.161290322580646,
      "rfg": 9.161290322580646,
      "cs_pct": 0.15384615384615385,
      "pb_g": 0.22580645161290322
    },
    "P9376": {
      "g": 31,
      "gs": 31,
      "pa": 129,
      "ab": 114,
      "r": 10,
      "h": 13,
      "b1": 10,
      "b2": 2,
      "b3": 0,
      "hr": 1,
      "rbi": 4,
      "bb": 8,
      "ibb": 0,
      "hbp": 6,
      "so": 41,
      "so_looking": 9,
      "so_swinging": 32,
      "sh": 0,
      "sf": 0,
      "roe": 0,
      "fc": 2,
      "ci": 0,
      "gidp": 3,
      "sb": 4,
      "cs": 0,
      "po": 67,
      "pocs": 0,
      "pitches": 473,
      "lob": 16,
      "lead": 18,
      "gb": 40,
      "ld": 19,
      "fb": 14,
      "tb": 18,
      "xbh": 3,
      "p_pa": 3.6666666666666665,
      "avg": 0.11403508771929824,
      "obp": 0.2109375,
      "slg": 0.15789473684210525,
      "ops": 0.36883223684210525,
      "iso": 0.043859649122807015,
      "babip": 0.16666666666666666,
      "bb_pct": 0.06201550387596899,
      "k_pct": 0.3178294573643411,
      "bb_k": 0.1951219512195122,
      "so_looking_pct": 0.21951219512195122,
      "sb_pct": 1.0,
      "gb_pct": 0.547945205479452,
      "ld_pct": 0.2602739726027397,
      "fb_pct": 0.1917808219178082,
      "gb_fb": 2.857142857142857,
      "ld_fb_ratio": 1.3571428571428572,
      "2b": 2,
      "3b": 0,
      "a": 6,
      "e": 2,
      "dp": 0,
      "tp": 0,
      "pk": 0,
      "pb": 0,
      "sba": 0,
      "tc": 75,
      "of_a": 6,
      "fpct": 0.9733333333333334,
      "rf9": 2.3548387096774195,
      "rfg": 2.3548387096774195,
      "cs_pct": 0.0,
      "pb_g": 0.0
    },
    "P6641": {
      "g": 24,
      "gs": 0,
      "pa": 36,
      "ab": 32,
      "r": 5,
      "h": 12,
      "b1": 8,
      "b2": 2,
      "b3": 0,
      "hr": 2,
      "rbi": 7,
      "bb": 3,
      "ibb": 0,
      "hbp": 0,
      "so": 4,
      "so_looking": 0,
      "so_swinging": 4,
      "sh": 0,
      "sf": 1,
      "roe": 2,
      "fc": 0,
      "ci": 0,
      "gidp": 0,
      "sb": 3,
      "cs": 0,
      "po": 6,
      "pocs": 0,
      "pitches": 133,
      "lob": 7,
      "lead": 1,
      "gb": 13,
      "ld": 6,
      "fb": 10,
      "tb": 20,
      "xbh": 4,
      "p_pa": 3.6944444444444446,
      "avg": 0.375,
      "obp": 0.4166666666666667,
      "slg": 0.625,
      "ops": 1.0416666666666667,
      "iso": 0.25,
      "babip": 0.37037037037037035,
      "bb_pct": 0.08333333333333333,
      "k_pct": 0.1111111111111111,
      "bb_k": 0.75,
      "so_looking_pct": 0.0,
      "sb_pct": 1.0,
      "gb_pct": 0.4482758620689655,
      "ld_pct": 0.20689655172413793,
      "fb_pct": 0.3448275862068966,
      "gb_fb": 1.3,
      "ld_fb_ratio": 0.6,
      "2b": 2,
      "3b": 0,
      "a": 7,
      "e": 0,
      "dp": 0,
      "tp": 0,
      "pk": 0,
      "pb": 0,
      "sba": 0,
      "tc": 13,
      "of_a": 0,
      "fpct": 1.0,
      "rf9": 0.5416666666666666,
      "rfg": 0.5416666666666666,
      "cs_pct": 0.0,
      "pb_g": 0.0
    },
    "P6548": {
      "g": 19,
      "gs": 0,
      "pa": 25,
      "ab": 24,
      "r": 1,
      "h": 6,
      "b1": 3,
      "b2": 3,
      "b3": 0,
      "hr": 0,
      "rbi": 2,
      "bb": 1,
      "ibb": 0,
      "hbp": 0,
      "so": 5,
      "so_looking": 0,
      "so_swinging": 5,
      "sh": 0,
      "sf": 0,
      "roe": 0,
      "fc": 1,
      "ci": 0,
      "gidp": 0,
      "sb": 1,
      "cs": 0,
      "po": 2,
      "pocs": 0,
      "pitches": 97,
      "lob": 7,
      "lead": 0,
      "gb": 8,
      "ld": 6,
      "fb": 5,
      "tb": 9,
      "xbh": 3,
      "p_pa": 3.88,
      "avg": 0.25,
      "obp": 0.28,
      "slg": 0.375,
      "ops": 0.655,
      "iso": 0.125,
      "babip": 0.3157894736842105,
      "bb_pct": 0.04,
      "k_pct": 0.2,
      "bb_k": 0.2,
      "so_looking_pct": 0.0,
      "sb_pct": 1.0,
      "gb_pct": 0.42105263157894735,
      "ld_pct": 0.3157894736842105,
      "fb_pct": 0.2631578947368421,
      "gb_fb": 1.6,
      "ld_fb_ratio": 1.2,
      "2b": 3,
      "3b": 0,
      "a": 6,
      "e": 0,
      "dp": 0,
      "tp": 0,
      "pk": 0,
      "pb": 0,
      "sba": 0,
      "tc": 8,
      "of_a": 0,
      "fpct": 1.0,
      "rf9": 0.42105263157894735,
      "rfg": 0.42105263157894735,
      "cs_pct": 0.0,
      "pb_g": 0.0
    },
    "P6098": {
      "g": 31,
      "gs": 31,
      "pa": 120,
      "ab": 105,
      "r": 14,
      "h": 28,
      "b1": 21,
      "b2": 4,
      "b3": 0,
      "hr": 3,
      "rbi": 14,
      "bb": 12,
      "ibb": 0,
      "hbp": 2,
      "so": 26,
      "so_looking": 9,
      "so_swinging": 17,
      "sh": 0,
      "sf": 1,
      "roe": 2,
      "fc": 0,
      "ci": 0,
      "gidp": 6,
      "sb": 4,
      "cs": 0,
      "po": 5,
      "pocs": 0,
      "pitches": 473,
      "lob": 26,
      "lead": 12,
      "gb": 41,
      "ld": 19,
      "fb": 20,
      "tb": 41,
      "xbh": 7,
      "p_pa": 3.941666666666667,
      "avg": 0.26666666666666666,
      "obp": 0.35,
      "slg": 0.3904761904761905,
      "ops": 0.7404761904761905,
      "iso": 0.12380952380952381,
      "babip": 0.3246753246753247,
      "bb_pct": 0.1,
      "k_pct": 0.21666666666666667,
      "bb_k": 0.46153846153846156,
      "so_looking_pct": 0.34615384615384615,
      "sb_pct": 1.0,
      "gb_pct": 0.5125,
      "ld_pct": 0.2375,
      "fb_pct": 0.25,
      "gb_fb": 2.05,
      "ld_fb_ratio": 0.95,
      "2b": 4,
      "3b": 0,
      "a": 22,
      "e": 1,
      "dp": 3,
      "tp": 0,
      "pk": 0,
      "pb": 0,
      "sba": 0,
      "tc": 28,
      "of_a": 0,
      "fpct": 0.9642857142857143,
      "rf9": 0.8709677419354839,
      "rfg": 0.8709677419354839,
      "cs_pct": 0.0,
      "pb_g": 0.0
    },
    "P7561": {
      "g": 31,
      "gs": 31,
      "pa": 120,
      "ab": 106,
      "r": 12,
      "h": 29,
      "b1": 17,
      "b2": 10,
      "b3": 0,
      "hr": 2,
      "rbi": 9,
      "bb": 10,
      "ibb": 0,
      "hbp": 2,
      "so": 31,
      "so_looking": 6,
      "so_swinging": 25,
      "sh": 2,
      "sf": 0,
      "roe": 0,
      "fc": 2,
      "ci": 0,
      "gidp": 2,
      "sb": 3,
      "cs": 0,
      "po": 67,
      "pocs": 0,
      "pitches": 469,
      "lob": 27,
      "lead": 9,
      "gb": 27,
      "ld": 14,
      "fb": 34,
      "tb": 45,
      "xbh": 12,
      "p_pa": 3.908333333333333,
      "avg": 0.27358490566037735,
      "obp": 0.3474576271186441,
      "slg": 0.42452830188679247,
      "ops": 0.7719859290054365,
      "iso": 0.15094339622641512,
      "babip": 0.3698630136986301,
      "bb_pct": 0.08333333333333333,
      "k_pct": 0.25833333333333336,
      "bb_k": 0.3225806451612903,
      "so_looking_pct": 0.1935483870967742,
      "sb_pct": 1.0,
      "gb_pct": 0.36,
      "ld_pct": 0.18666666666666668,
      "fb_pct": 0.4533333333333333,
      "gb_fb": 0.7941176470588235,
      "ld_fb_ratio": 0.4117647058823529,
      "2b": 10,
      "3b": 0,
      "a": 3,
      "e": 1,
      "dp": 0,
      "tp": 0,
      "pk": 0,
      "pb": 0,
      "sba": 0,
      "tc": 71,
      "of_a": 3,
      "fpct": 0.9859154929577465,
      "rf9": 2.2580645161290325,
      "rfg": 2.2580645161290325,
      "cs_pct": 0.0,
      "pb_g": 0.0
    },
    "P1460": {
      "g": 31,
      "gs": 31,
      "pa": 98,
      "ab": 86,
      "r": 9,
      "h": 17,
      "b1": 10,
      "b2": 6,
      "b3": 0,
      "hr": 1,
      "rbi": 6,
      "bb": 9,
      "ibb": 0,
      "hbp": 1,
      "so": 22,
      "so_looking": 4,
      "so_swinging": 18,
      "sh": 0,
      "sf": 1,
      "roe": 1,
      "fc": 0,
      "ci": 1,
      "gidp": 3,
      "sb": 3,
      "cs": 0,
      "po": 27,
      "pocs": 0,
      "pitches": 416,
      "lob": 15,
      "lead": 5,
      "gb": 33,
      "ld": 7,
      "fb": 25,
      "tb": 26,
      "xbh": 7,
      "p_pa": 4.244897959183674,
      "avg": 0.19767441860465115,
      "obp": 0.27835051546391754,
      "slg": 0.3023255813953488,
      "ops": 0.5806760968592664,
      "iso": 0.10465116279069767,
      "babip": 0.25,
      "bb_pct": 0.09183673469387756,
      "k_pct": 0.22448979591836735,
      "bb_k": 0.4090909090909091,
      "so_looking_pct": 0.18181818181818182,
      "sb_pct": 1.0,
      "gb_pct": 0.5076923076923077,
      "ld_pct": 0.1076923076923077,
      "fb_pct": 0.38461538461538464,
      "gb_fb": 1.32,
      "ld_fb_ratio": 0.28,
      "2b": 6,
      "3b": 0,
      "a": 118,
      "e": 2,
      "dp": 10,
      "tp": 0,
      "pk": 0,
      "pb": 0,
      "sba": 0,
      "tc": 147,
      "of_a": 0,
      "fpct": 0.9863945578231292,
      "rf9": 4.67741935483871,
      "rfg": 4.67741935483871,
      "cs_pct": 0.0,
      "pb_g": 0.0
    },
    "P7048": {
      "g": 31,
      "gs": 31,
      "pa": 144,
      "ab": 133,
      "r": 19,
      "h": 32,
      "b1": 15,
      "b2": 10,
      "b3": 4,
      "hr": 3,
      "rbi": 13,
      "bb": 9,
      "ibb": 0,
      "hbp": 2,
      "so": 27,
      "so_looking": 5,
      "so_swinging": 22,
      "sh": 0,
      "sf": 0,
      "roe": 3,
      "fc": 1,
      "ci": 0,
      "gidp": 3,
      "sb": 8,
      "cs": 1,
      "po": 6,
      "pocs": 0,
      "pitches": 515,
      "lob": 27,
      "lead": 514,
      "gb": 50,
      "ld": 15,
      "fb": 40,
      "tb": 59,
      "xbh": 17,
      "p_pa": 3.576388888888889,
      "avg": 0.24060150375939848,
      "obp": 0.2986111111111111,
      "slg": 0.44360902255639095,
      "ops": 0.7422201336675021,
      "iso": 0.20300751879699247,
      "babip": 0.2815533980582524,
      "bb_pct": 0.0625,
      "k_pct": 0.1875,
      "bb_k": 0.3333333333333333,
      "so_looking_pct": 0.18518518518518517,
      "sb_pct": 0.8888888888888888,
      "gb_pct": 0.47619047619047616,
      "ld_pct": 0.14285714285714285,
      "fb_pct": 0.38095238095238093,
      "gb_fb": 1.25,
      "ld_fb_ratio": 0.375,
      "2b": 10,
      "3b": 4,
      "a": 22,
      "e": 2,
      "dp": 0,
      "tp": 0,
      "pk": 0,
      "pb": 0,
      "sba": 0,
      "tc": 30,
      "of_a": 0,
      "fpct": 0.9333333333333333,
      "rf9": 0.9032258064516129,
      "rfg": 0.9032258064516129,
      "cs_pct": 0.0,
      "pb_g": 0.0
    },
    "P3338": {
      "g": 31,
      "gs": 31,
      "pa": 142,
      "ab": 131,
      "r": 12,
      "h": 27,
      "b1": 18,
      "b2": 3,
      "b3": 3,
      "hr": 3,
      "rbi": 11,
      "bb": 10,
      "ibb": 0,
      "hbp": 0,
      "so": 35,
      "so_looking": 11,
      "so_swinging": 24,
      "sh": 1,
      "sf": 0,
      "roe": 0,
      "fc": 0,
      "ci": 0,
      "gidp": 1,
      "sb": 10,
      "cs": 0,
      "po": 89,
      "pocs": 0,
      "pitches": 546,
      "lob": 22,
      "lead": 332,
      "gb": 42,
      "ld": 20,
      "fb": 34,
      "tb": 45,
      "xbh": 9,
      "p_pa": 3.8450704225352115,
      "avg": 0.20610687022900764,
      "obp": 0.2624113475177305,
      "slg": 0.3435114503816794,
      "ops": 0.60592279789941,
      "iso": 0.13740458015267176,
      "babip": 0.25806451612903225,
      "bb_pct": 0.07042253521126761,
      "k_pct": 0.24647887323943662,
      "bb_k": 0.2857142857142857,
      "so_looking_pct": 0.3142857142857143,
      "sb_pct": 1.0,
      "gb_pct": 0.4375,
      "ld_pct": 0.20833333333333334,
      "fb_pct": 0.3541666666666667,
      "gb_fb": 1.2352941176470589,
      "ld_fb_ratio": 0.5882352941176471,
      "2b": 3,
      "3b": 3,
      "a": 5,
      "e": 0,
      "dp": 0,
      "tp": 0,
      "pk": 0,
      "pb": 0,
      "sba": 0,
      "tc": 94,
      "of_a": 5,
      "fpct": 1.0,
      "rf9": 3.032258064516129,
      "rfg": 3.032258064516129,
      "cs_pct": 0.0,
      "pb_g": 0.0
    },
    "P9028": {
      "g": 1,
      "gs": 0,
      "pa": 3,
      "ab": 2,
      "r": 0,
      "h": 0,
      "b1": 0,
      "b2": 0,
      "b3": 0,
      "hr": 0,
      "rbi": 0,
      "bb": 1,
      "ibb": 0,
      "hbp": 0,
      "so": 2,
      "so_looking": 1,
      "so_swinging": 1,
      "sh": 0,
      "sf": 0,
      "roe": 0,
      "fc": 0,
      "ci": 0,
      "gidp": 0,
      "sb": 0,
      "cs": 0,
      "po": 2,
      "pocs": 0,
      "pitches": 21,
      "lob": 2,
      "lead": 0,
      "gb": 0,
      "ld": 0,
      "fb": 0,
      "tb": 0,
      "xbh": 0,
      "p_pa": 7.0,
      "avg": 0.0,
      "obp": 0.3333333333333333,
      "slg": 0.0,
      "ops": 0.3333333333333333,
      "iso": 0.0,
      "babip": 0.0,
      "bb_pct": 0.3333333333333333,
      "k_pct": 0.6666666666666666,
      "bb_k": 0.5,
      "so_looking_pct": 0.5,
      "sb_pct": 0.0,
      "gb_pct": 0.0,
      "ld_pct": 0.0,
      "fb_pct": 0.0,
      "gb_fb": 0.0,
      "ld_fb_ratio": 0.0,
      "2b": 0,
      "3b": 0,
      "a": 0,
      "e": 0,
      "dp": 0,
      "tp": 0,
      "pk": 0,
      "pb": 0,
      "sba": 0,
      "tc": 2,
      "of_a": 0,
      "fpct": 1.0,
      "rf9": 2.0,
      "rfg": 2.0,
      "cs_pct": 0.0,
      "pb_g": 0.0
    },
    "P7862": {
      "g": 31,
      "gs": 31,
      "pa": 135,
      "ab": 120,
      "r": 14,
      "h": 23,
      "b1": 18,
      "b2": 2,
      "b3": 0,
      "hr": 3,
      "rbi": 11,
      "bb": 8,
      "ibb": 0,
      "hbp": 5,
      "so": 36,
      "so_looking": 8,
      "so_swinging": 28,
      "sh": 1,
      "sf": 1,
      "roe": 0,
      "fc": 3,
      "ci": 0,
      "gidp": 2,
      "sb": 10,
      "cs": 1,
      "po": 0,
      "pocs": 0,
      "pitches": 517,
      "lob": 24,
      "lead": 123,
      "gb": 37,
      "ld": 19,
      "fb": 29,
      "tb": 34,
      "xbh": 5,
      "p_pa": 3.8296296296296295,
      "avg": 0.19166666666666668,
      "obp": 0.26865671641791045,
      "slg": 0.2833333333333333,
      "ops": 0.5519900497512438,
      "iso": 0.09166666666666665,
      "babip": 0.24390243902439024,
      "bb_pct": 0.05925925925925926,
      "k_pct": 0.26666666666666666,
      "bb_k": 0.2222222222222222,
      "so_looking_pct": 0.2222222222222222,
      "sb_pct": 0.9090909090909091,
      "gb_pct": 0.43529411764705883,
      "ld_pct": 0.2235294117647059,
      "fb_pct": 0.3411764705882353,
      "gb_fb": 1.2758620689655173,
      "ld_fb_ratio": 0.6551724137931034,
      "2b": 2,
      "3b": 0
    },
    "P6248": {
      "g": 31,
      "gs": 31,
      "pa": 123,
      "ab": 109,
      "r": 14,
      "h": 27,
      "b1": 19,
      "b2": 4,
      "b3": 0,
      "hr": 4,
      "rbi": 9,
      "bb": 14,
      "ibb": 0,
      "hbp": 0,
      "so": 27,
      "so_looking": 5,
      "so_swinging": 22,
      "sh": 0,
      "sf": 0,
      "roe": 2,
      "fc": 1,
      "ci": 1,
      "gidp": 0,
      "sb": 9,
      "cs": 4,
      "po": 280,
      "pocs": 0,
      "pitches": 421,
      "lob": 31,
      "lead": 151,
      "gb": 34,
      "ld": 10,
      "fb": 37,
      "tb": 43,
      "xbh": 8,
      "p_pa": 3.4227642276422765,
      "avg": 0.24770642201834864,
      "obp": 0.3333333333333333,
      "slg": 0.3944954128440367,
      "ops": 0.72782874617737,
      "iso": 0.14678899082568808,
      "babip": 0.2948717948717949,
      "bb_pct": 0.11382113821138211,
      "k_pct": 0.21951219512195122,
      "bb_k": 0.5185185185185185,
      "so_looking_pct": 0.18518518518518517,
      "sb_pct": 0.6923076923076923,
      "gb_pct": 0.41975308641975306,
      "ld_pct": 0.12345679012345678,
      "fb_pct": 0.4567901234567901,
      "gb_fb": 0.918918918918919,
      "ld_fb_ratio": 0.2702702702702703,
      "2b": 4,
      "3b": 0,
      "a": 4,
      "e": 0,
      "dp": 0,
      "tp": 0,
      "pk": 0,
      "pb": 12,
      "sba": 51,
      "tc": 284,
      "of_a": 0,
      "fpct": 1.0,
      "rf9": 9.161290322580646,
      "rfg": 9.161290322580646,
      "cs_pct": 0.0784313725490196,
      "pb_g": 0.3870967741935484
    },
    "P5113": {
      "g": 31,
      "gs": 31,
      "pa": 130,
      "ab": 121,
      "r": 10,
      "h": 25,
      "b1": 15,
      "b2": 8,
      "b3": 2,
      "hr": 0,
      "rbi": 5,
      "bb": 7,
      "ibb": 0,
      "hbp": 1,
      "so": 41,
      "so_looking": 10,
      "so_swinging": 31,
      "sh": 0,
      "sf": 1,
      "roe": 0,
      "fc": 1,
      "ci": 0,
      "gidp": 1,
      "sb": 6,
      "cs": 0,
      "po": 70,
      "pocs": 0,
      "pitches": 564,
      "lob": 21,
      "lead": 103,
      "gb": 25,
      "ld": 20,
      "fb": 36,
      "tb": 37,
      "xbh": 10,
      "p_pa": 4.338461538461538,
      "avg": 0.2066115702479339,
      "obp": 0.25384615384615383,
      "slg": 0.30578512396694213,
      "ops": 0.559631277813096,
      "iso": 0.09917355371900824,
      "babip": 0.30864197530864196,
      "bb_pct": 0.05384615384615385,
      "k_pct": 0.3153846153846154,
      "bb_k": 0.17073170731707318,
      "so_looking_pct": 0.24390243902439024,
      "sb_pct": 1.0,
      "gb_pct": 0.30864197530864196,
      "ld_pct": 0.24691358024691357,
      "fb_pct": 0.4444444444444444,
      "gb_fb": 0.6944444444444444,
      "ld_fb_ratio": 0.5555555555555556,
      "2b": 8,
      "3b": 2,
      "a": 0,
      "e": 3,
      "dp": 0,
      "tp": 0,
      "pk": 0,
      "pb": 0,
      "sba": 0,
      "tc": 73,
      "of_a": 0,
      "fpct": 0.958904109589041,
      "rf9": 2.2580645161290325,
      "rfg": 2.2580645161290325,
      "cs_pct": 0.0,
      "pb_g": 0.0
    },
    "P4954": {
      "g": 31,
      "gs": 31,
      "pa": 125,
      "ab": 113,
      "r": 13,
      "h": 32,
      "b1": 18,
      "b2": 6,
      "b3": 0,
      "hr": 8,
      "rbi": 20,
      "bb": 8,
      "ibb": 0,
      "hbp": 0,
      "so": 23,
      "so_looking": 6,
      "so_swinging": 17,
      "sh": 0,
      "sf": 4,
      "roe": 1,
      "fc": 1,
      "ci": 0,
      "gidp": 2,
      "sb": 4,
      "cs": 0,
      "po": 24,
      "pocs": 0,
      "pitches": 480,
      "lob": 24,
      "lead": 4,
      "gb": 43,
      "ld": 14,
      "fb": 37,
      "tb": 62,
      "xbh": 14,
      "p_pa": 3.84,
      "avg": 0.2831858407079646,
      "obp": 0.32,
      "slg": 0.5486725663716814,
      "ops": 0.8686725663716814,
      "iso": 0.2654867256637168,
      "babip": 0.27906976744186046,
      "bb_pct": 0.064,
      "k_pct": 0.184,
      "bb_k": 0.34782608695652173,
      "so_looking_pct": 0.2608695652173913,
      "sb_pct": 1.0,
      "gb_pct": 0.4574468085106383,
      "ld_pct": 0.14893617021276595,
      "fb_pct": 0.39361702127659576,
      "gb_fb": 1.162162162162162,
      "ld_fb_ratio": 0.3783783783783784,
      "2b": 6,
      "3b": 0,
      "a": 118,
      "e": 2,
      "dp": 12,
      "tp": 0,
      "pk": 0,
      "pb": 0,
      "sba": 0,
      "tc": 144,
      "of_a": 0,
      "fpct": 0.9861111111111112,
      "rf9": 4.580645161290323,
      "rfg": 4.580645161290323,
      "cs_pct": 0.0,
      "pb_g": 0.0
    },
    "P4630": {
      "g": 31,
      "gs": 31,
      "pa": 122,
      "ab": 111,
      "r": 6,
      "h": 27,
      "b1": 18,
      "b2": 7,
      "b3": 0,
      "hr": 2,
      "rbi": 9,
      "bb": 8,
      "ibb": 0,
      "hbp": 2,
      "so": 20,
      "so_looking": 9,
      "so_swinging": 11,
      "sh": 0,
      "sf": 0,
      "roe": 0,
      "fc": 2,
      "ci": 0,
      "gidp": 0,
      "sb": 2,
      "cs": 1,
      "po": 30,
      "pocs": 0,
      "pitches": 470,
      "lob": 25,
      "lead": 5,
      "gb": 42,
      "ld": 22,
      "fb": 27,
      "tb": 40,
      "xbh": 9,
      "p_pa": 3.8524590163934427,
      "avg": 0.24324324324324326,
      "obp": 0.30578512396694213,
      "slg": 0.36036036036036034,
      "ops": 0.6661454843273025,
      "iso": 0.11711711711711709,
      "babip": 0.2808988764044944,
      "bb_pct": 0.06557377049180328,
      "k_pct": 0.16393442622950818,
      "bb_k": 0.4,
      "so_looking_pct": 0.45,
      "sb_pct": 0.6666666666666666,
      "gb_pct": 0.46153846153846156,
      "ld_pct": 0.24175824175824176,
      "fb_pct": 0.2967032967032967,
      "gb_fb": 1.5555555555555556,
      "ld_fb_ratio": 0.8148148148148148,
      "2b": 7,
      "3b": 0,
      "a": 118,
      "e": 2,
      "dp": 13,
      "tp": 0,
      "pk": 0,
      "pb": 0,
      "sba": 0,
      "tc": 150,
      "of_a": 0,
      "fpct": 0.9866666666666667,
      "rf9": 4.774193548387097,
      "rfg": 4.774193548387097,
      "cs_pct": 0.0,
      "pb_g": 0.0
    },
    "P2080": {
      "g": 31,
      "gs": 31,
      "pa": 117,
      "ab": 108,
      "r": 11,
      "h": 20,
      "b1": 11,
      "b2": 5,
      "b3": 0,
      "hr": 4,
      "rbi": 7,
      "bb": 5,
      "ibb": 0,
      "hbp": 1,
      "so": 31,
      "so_looking": 6,
      "so_swinging": 25,
      "sh": 1,
      "sf": 0,
      "roe": 1,
      "fc": 2,
      "ci": 1,
      "gidp": 2,
      "sb": 2,
      "cs": 0,
      "po": 268,
      "pocs": 0,
      "pitches": 474,
      "lob": 15,
      "lead": 4,
      "gb": 38,
      "ld": 12,
      "fb": 27,
      "tb": 37,
      "xbh": 9,
      "p_pa": 4.051282051282051,
      "avg": 0.18518518518518517,
      "obp": 0.22807017543859648,
      "slg": 0.3425925925925926,
      "ops": 0.5706627680311891,
      "iso": 0.15740740740740744,
      "babip": 0.2191780821917808,
      "bb_pct": 0.042735042735042736,
      "k_pct": 0.26495726495726496,
      "bb_k": 0.16129032258064516,
      "so_looking_pct": 0.1935483870967742,
      "sb_pct": 1.0,
      "gb_pct": 0.4935064935064935,
      "ld_pct": 0.15584415584415584,
      "fb_pct": 0.35064935064935066,
      "gb_fb": 1.4074074074074074,
      "ld_fb_ratio": 0.4444444444444444,
      "2b": 5,
      "3b": 0,
      "a": 0,
      "e": 1,
      "dp": 14,
      "tp": 0,
      "pk": 0,
      "pb": 0,
      "sba": 0,
      "tc": 269,
      "of_a": 0,
      "fpct": 0.9962825278810409,
      "rf9": 8.64516129032258,
      "rfg": 8.64516129032258,
      "cs_pct": 0.0,
      "pb_g": 0.0
    },
    "P9255": {
      "g": 31,
      "gs": 31,
      "pa": 136,
      "ab": 124,
      "r": 10,
      "h": 27,
      "b1": 17,
      "b2": 3,
      "b3": 1,
      "hr": 6,
      "rbi": 18,
      "bb": 9,
      "ibb": 0,
      "hbp": 1,
      "so": 48,
      "so_looking": 9,
      "so_swinging": 39,
      "sh": 0,
      "sf": 1,
      "roe": 1,
      "fc": 1,
      "ci": 1,
      "gidp": 1,
      "sb": 5,
      "cs": 0,
      "po": 72,
      "pocs": 0,
      "pitches": 568,
      "lob": 23,
      "lead": 5,
      "gb": 34,
      "ld": 20,
      "fb": 23,
      "tb": 50,
      "xbh": 10,
      "p_pa": 4.176470588235294,
      "avg": 0.21774193548387097,
      "obp": 0.2740740740740741,
      "slg": 0.4032258064516129,
      "ops": 0.6772998805256869,
      "iso": 0.1854838709677419,
      "babip": 0.29577464788732394,
      "bb_pct": 0.0661764705882353,
      "k_pct": 0.35294117647058826,
      "bb_k": 0.1875,
      "so_looking_pct": 0.1875,
      "sb_pct": 1.0,
      "gb_pct": 0.44155844155844154,
      "ld_pct": 0.2597402597402597,
      "fb_pct": 0.2987012987012987,
      "gb_fb": 1.4782608695652173,
      "ld_fb_ratio": 0.8695652173913043,
      "2b": 3,
      "3b": 1,
      "a": 3,
      "e": 5,
      "dp": 0,
      "tp": 0,
      "pk": 0,
      "pb": 0,
      "sba": 0,
      "tc": 80,
      "of_a": 3,
      "fpct": 0.9375,
      "rf9": 2.4193548387096775,
      "rfg": 2.4193548387096775,
      "cs_pct": 0.0,
      "pb_g": 0.0
    },
    "P7674": {
      "g": 7,
      "gs": 7,
      "w": 2,
      "l": 2,
      "gf": 0,
      "sv": 0,
      "svo": 0,
      "hld": 0,
      "bs": 0,
      "ir": 0,
      "irs": 0,
      "bf": 154,
      "outs": 110,
      "r": 21,
      "er": 19,
      "h": 31,
      "b1": 16,
      "b2": 8,
      "b3": 2,
      "hr": 5,
      "bb": 9,
      "ibb": 0,
      "so": 45,
      "so_looking": 6,
      "so_swinging": 39,
      "hbp": 1,
      "wp": 4,
      "bk": 0,
      "pk": 0,
      "pocs": 0,
      "pitches_thrown": 611,
      "balls_thrown": 203,
      "strikes_thrown": 408,
      "first_pitch_strikes": 100,
      "zone_pitches": 313,
      "o_zone_pitches": 298,
      "zone_swings": 206,
      "o_zone_swings": 101,
      "zone_contacts": 175,
      "o_zone_contacts": 65,
      "gb": 45,
      "ld": 15,
      "fb": 39,
      "ip": 36.666666666666664,
      "cg": 0,
      "sho": 0,
      "qs": 0,
      "k_minus_bb": 36,
      "h9": 7.609090909090909,
      "hr9": 1.2272727272727273,
      "k9": 11.045454545454547,
      "bb9": 2.2090909090909094,
      "era": 4.663636363636364,
      "whip": 1.090909090909091,
      "k_bb": 5.0,
      "fip": 3.3363636363636364,
      "lob_pct": 0.5882352941176471,
      "fps_pct": 0.6493506493506493,
      "zone_pct": 0.5122749590834698,
      "z_swing_pct": 0.65814696485623,
      "z_contact_pct": 0.8495145631067961,
      "ozone_pct": 0.4877250409165303,
      "ozone_swing_pct": 0.3389261744966443,
      "ozone_contact_pct": 0.6435643564356436,
      "swstr_pct": 0.10965630114566285,
      "so_looking_pct": 0.13333333333333333,
      "gb_pct": 0.45454545454545453,
      "ld_pct": 0.15151515151515152,
      "fb_pct": 0.3939393939393939,
      "gb_fb": 1.1538461538461537,
      "ld_fb_ratio": 0.38461538461538464,
      "po": 0,
      "a": 44,
      "e": 0,
      "dp": 0,
      "tp": 0,
      "pb": 0,
      "ci": 0,
      "cs": 0,
      "sba": 0,
      "tc": 44,
      "of_a": 0,
      "fpct": 1.0,
      "rf9": 6.285714285714286,
      "rfg": 6.285714285714286,
      "cs_pct": 0.0,
      "pb_g": 0.0
    },
    "P9305": {
      "g": 6,
      "gs": 0,
      "w": 0,
      "l": 0,
      "gf": 0,
      "sv": 0,
      "svo": 0,
      "hld": 0,
      "bs": 0,
      "ir": 12,
      "irs": 5,
      "bf": 52,
      "outs": 37,
      "r": 0,
      "er": 0,
      "h": 6,
      "b1": 4,
      "b2": 2,
      "b3": 0,
      "hr": 0,
      "bb": 6,
      "ibb": 0,
      "so": 13,
      "so_looking": 4,
      "so_swinging": 9,
      "hbp": 3,
      "wp": 1,
      "bk": 0,
      "pk": 0,
      "pocs": 0,
      "pitches_thrown": 204,
      "balls_thrown": 76,
      "strikes_thrown": 128,
      "first_pitch_strikes": 38,
      "zone_pitches": 92,
      "o_zone_pitches": 112,
      "zone_swings": 56,
      "o_zone_swings": 40,
      "zone_contacts": 49,
      "o_zone_contacts": 26,
      "gb": 15,
      "ld": 8,
      "fb": 7,
      "ip": 12.333333333333334,
      "cg": 0,
      "sho": 0,
      "qs": 0,
      "k_minus_bb": 7,
      "h9": 4.378378378378378,
      "hr9": 0.0,
      "k9": 9.486486486486486,
      "bb9": 4.378378378378378,
      "era": 0.0,
      "whip": 0.9729729729729729,
      "k_bb": 2.1666666666666665,
      "fip": 3.2810810810810813,
      "lob_pct": 1.0,
      "fps_pct": 0.7307692307692307,
      "zone_pct": 0.45098039215686275,
      "z_swing_pct": 0.6086956521739131,
      "z_contact_pct": 0.875,
      "ozone_pct": 0.5490196078431373,
      "ozone_swing_pct": 0.35714285714285715,
      "ozone_contact_pct": 0.65,
      "swstr_pct": 0.10294117647058823,
      "so_looking_pct": 0.3076923076923077,
      "gb_pct": 0.5,
      "ld_pct": 0.26666666666666666,
      "fb_pct": 0.23333333333333334,
      "gb_fb": 2.142857142857143,
      "ld_fb_ratio": 1.1428571428571428,
      "po": 0,
      "a": 12,
      "e": 0,
      "dp": 0,
      "tp": 0,
      "pb": 0,
      "ci": 0,
      "cs": 0,
      "sba": 0,
      "tc": 12,
      "of_a": 0,
      "fpct": 1.0,
      "rf9": 2.0,
      "rfg": 2.0,
      "cs_pct": 0.0,
      "pb_g": 0.0
    },
    "P6112": {
      "g": 11,
      "gs": 0,
      "w": 1,
      "l": 2,
      "gf": 8,
      "sv": 0,
      "svo": 2,
      "hld": 1,
      "bs": 1,
      "ir": 2,
      "irs": 0,
      "bf": 97,
      "outs": 63,
      "r": 10,
      "er": 9,
      "h": 18,
      "b1": 11,
      "b2": 7,
      "b3": 0,
      "hr": 0,
      "bb": 12,
      "ibb": 0,
      "so": 26,
      "so_looking": 7,
      "so_swinging": 19,
      "hbp": 2,
      "wp": 0,
      "bk": 0,
      "pk": 0,
      "pocs": 0,
      "pitches_thrown": 395,
      "balls_thrown": 148,
      "strikes_thrown": 247,
      "first_pitch_strikes": 52,
      "zone_pitches": 192,
      "o_zone_pitches": 203,
      "zone_swings": 112,
      "o_zone_swings": 60,
      "zone_contacts": 96,
      "o_zone_contacts": 38,
      "gb": 23,
      "ld": 19,
      "fb": 13,
      "ip": 21.0,
      "cg": 0,
      "sho": 0,
      "qs": 0,
      "k_minus_bb": 14,
      "h9": 7.714285714285714,
      "hr9": 0.0,
      "k9": 11.142857142857142,
      "bb9": 5.142857142857143,
      "era": 3.857142857142857,
      "whip": 1.4285714285714286,
      "k_bb": 2.1666666666666665,
      "fip": 2.723809523809524,
      "lob_pct": 0.6875,
      "fps_pct": 0.5360824742268041,
      "zone_pct": 0.4860759493670886,
      "z_swing_pct": 0.5833333333333334,
      "z_contact_pct": 0.8571428571428571,
      "ozone_pct": 0.5139240506329114,
      "ozone_swing_pct": 0.2955665024630542,
      "ozone_contact_pct": 0.6333333333333333,
      "swstr_pct": 0.09620253164556962,
      "so_looking_pct": 0.2692307692307692,
      "gb_pct": 0.41818181818181815,
      "ld_pct": 0.34545454545454546,
      "fb_pct": 0.23636363636363636,
      "gb_fb": 1.7692307692307692,
      "ld_fb_ratio": 1.4615384615384615,
      "po": 0,
      "a": 26,
      "e": 0,
      "dp": 0,
      "tp": 0,
      "pb": 0,
      "ci": 0,
      "cs": 0,
      "sba": 0,
      "tc": 26,
      "of_a": 0,
      "fpct": 1.0,
      "rf9": 2.3636363636363638,
      "rfg": 2.3636363636363638,
      "cs_pct": 0.0,
      "pb_g": 0.0
    },
    "P2649": {
      "g": 11,
      "gs": 0,
      "w": 0,
      "l": 2,
      "gf": 11,
      "sv": 9,
      "svo": 11,
      "hld": 0,
      "bs": 2,
      "ir": 0,
      "irs": 0,
      "bf": 53,
      "outs": 33,
      "r": 7,
      "er": 7,
      "h": 13,
      "b1": 7,
      "b2": 4,
      "b3": 0,
      "hr": 2,
      "bb": 7,
      "ibb": 0,
      "so": 15,
      "so_looking": 3,
      "so_swinging": 12,
      "hbp": 1,
      "wp": 2,
      "bk": 0,
      "pk": 0,
      "pocs": 0,
      "pitches_thrown": 229,
      "balls_thrown": 83,
      "strikes_thrown": 146,
      "first_pitch_strikes": 39,
      "zone_pitches": 109,
      "o_zone_pitches": 120,
      "zone_swings": 68,
      "o_zone_swings": 39,
      "zone_contacts": 61,
      "o_zone_contacts": 25,
      "gb": 14,
      "ld": 7,
      "fb": 9,
      "ip": 11.0,
      "cg": 0,
      "sho": 0,
      "qs": 0,
      "k_minus_bb": 8,
      "h9": 10.636363636363637,
      "hr9": 1.6363636363636365,
      "k9": 12.272727272727273,
      "bb9": 5.7272727272727275,
      "era": 5.7272727272727275,
      "whip": 1.8181818181818181,
      "k_bb": 2.142857142857143,
      "fip": 5.0181818181818185,
      "lob_pct": 0.7692307692307693,
      "fps_pct": 0.7358490566037735,
      "zone_pct": 0.4759825327510917,
      "z_swing_pct": 0.6238532110091743,
      "z_contact_pct": 0.8970588235294118,
      "ozone_pct": 0.5240174672489083,
      "ozone_swing_pct": 0.325,
      "ozone_contact_pct": 0.6410256410256411,
      "swstr_pct": 0.09170305676855896,
      "so_looking_pct": 0.2,
      "gb_pct": 0.4666666666666667,
      "ld_pct": 0.23333333333333334,
      "fb_pct": 0.3,
      "gb_fb": 1.5555555555555556,
      "ld_fb_ratio": 0.7777777777777778,
      "po": 0,
      "a": 15,
      "e": 0,
      "dp": 0,
      "tp": 0,
      "pb": 0,
      "ci": 0,
      "cs": 0,
      "sba": 0,
      "tc": 15,
      "of_a": 0,
      "fpct": 1.0,
      "rf9": 1.3636363636363635,
      "rfg": 1.3636363636363635,
      "cs_pct": 0.0,
      "pb_g": 0.0
    },
    "P8084": {
      "g": 7,
      "gs": 7,
      "w": 2,
      "l": 0,
      "gf": 0,
      "sv": 0,
      "svo": 0,
      "hld": 0,
      "bs": 0,
      "ir": 0,
      "irs": 0,
      "bf": 182,
      "outs": 136,
      "r": 14,
      "er": 14,
      "h": 36,
      "b1": 23,
      "b2": 10,
      "b3": 0,
      "hr": 3,
      "bb": 13,
      "ibb": 0,
      "so": 42,
      "so_looking": 12,
      "so_swinging": 30,
      "hbp": 1,
      "wp": 4,
      "bk": 0,
      "pk": 0,
      "pocs": 0,
      "pitches_thrown": 697,
      "balls_thrown": 234,
      "strikes_thrown": 463,
      "first_pitch_strikes": 118,
      "zone_pitches": 345,
      "o_zone_pitches": 352,
      "zone_swings": 220,
      "o_zone_swings": 122,
      "zone_contacts": 194,
      "o_zone_contacts": 84,
      "gb": 61,
      "ld": 19,
      "fb": 43,
      "ip": 45.333333333333336,
      "cg": 0,
      "sho": 0,
      "qs": 0,
      "k_minus_bb": 29,
      "h9": 7.147058823529411,
      "hr9": 0.5955882352941176,
      "k9": 8.338235294117647,
      "bb9": 2.580882352941176,
      "era": 2.7794117647058822,
      "whip": 1.0808823529411764,
      "k_bb": 3.230769230769231,
      "fip": 3.1338235294117647,
      "lob_pct": 0.7860262008733625,
      "fps_pct": 0.6483516483516484,
      "zone_pct": 0.4949784791965567,
      "z_swing_pct": 0.6376811594202898,
      "z_contact_pct": 0.8818181818181818,
      "ozone_pct": 0.5050215208034433,
      "ozone_swing_pct": 0.3465909090909091,
      "ozone_contact_pct": 0.6885245901639344,
      "swstr_pct": 0.09182209469153516,
      "so_looking_pct": 0.2857142857142857,
      "gb_pct": 0.4959349593495935,
      "ld_pct": 0.15447154471544716,
      "fb_pct": 0.34959349593495936,
      "gb_fb": 1.4186046511627908,
      "ld_fb_ratio": 0.4418604651162791,
      "po": 0,
      "a": 41,
      "e": 0,
      "dp": 0,
      "tp": 0,
      "pb": 0,
      "ci": 0,
      "cs": 0,
      "sba": 0,
      "tc": 41,
      "of_a": 0,
      "fpct": 1.0,
      "rf9": 5.857142857142857,
      "rfg": 5.857142857142857,
      "cs_pct": 0.0,
      "pb_g": 0.0
    },
    "P6684": {
      "g": 15,
      "gs": 0,
      "w": 0,
      "l": 0,
      "gf": 0,
      "sv": 0,
      "svo": 5,
      "hld": 5,
      "bs": 0,
      "ir": 10,
      "irs": 4,
      "bf": 61,
      "outs": 47,
      "r": 4,
      "er": 4,
      "h": 10,
      "b1": 6,
      "b2": 3,
      "b3": 0,
      "hr": 1,
      "bb": 4,
      "ibb": 0,
      "so": 16,
      "so_looking": 3,
      "so_swinging": 13,
      "hbp": 1,
      "wp": 0,
      "bk": 0,
      "pk": 0,
      "pocs": 0,
      "pitches_thrown": 252,
      "balls_thrown": 83,
      "strikes_thrown": 169,
      "first_pitch_strikes": 31,
      "zone_pitches": 117,
      "o_zone_pitches": 135,
      "zone_swings": 74,
      "o_zone_swings": 53,
      "zone_contacts": 64,
      "o_zone_contacts": 35,
      "gb": 12,
      "ld": 10,
      "fb": 18,
      "ip": 15.666666666666666,
      "cg": 0,
      "sho": 0,
      "qs": 0,
      "k_minus_bb": 12,
      "h9": 5.74468085106383,
      "hr9": 0.574468085106383,
      "k9": 9.191489361702128,
      "bb9": 2.297872340425532,
      "era": 2.297872340425532,
      "whip": 0.8936170212765958,
      "k_bb": 4.0,
      "fip": 2.94468085106383,
      "lob_pct": 0.8088235294117647,
      "fps_pct": 0.5081967213114754,
      "zone_pct": 0.4642857142857143,
      "z_swing_pct": 0.6324786324786325,
      "z_contact_pct": 0.8648648648648649,
      "ozone_pct": 0.5357142857142857,
      "ozone_swing_pct": 0.3925925925925926,
      "ozone_contact_pct": 0.660377358490566,
      "swstr_pct": 0.1111111111111111,
      "so_looking_pct": 0.1875,
      "gb_pct": 0.3,
      "ld_pct": 0.25,
      "fb_pct": 0.45,
      "gb_fb": 0.6666666666666666,
      "ld_fb_ratio": 0.5555555555555556,
      "po": 0,
      "a": 16,
      "e": 0,
      "dp": 0,
      "tp": 0,
      "pb": 0,
      "ci": 0,
      "cs": 0,
      "sba": 0,
      "tc": 16,
      "of_a": 0,
      "fpct": 1.0,
      "rf9": 1.0666666666666667,
      "rfg": 1.0666666666666667,
      "cs_pct": 0.0,
      "pb_g": 0.0
    },
    "P7028": {
      "g": 10,
      "gs": 0,
      "w": 0,
      "l": 1,
      "gf": 1,
      "sv": 0,
      "svo": 7,
      "hld": 6,
      "bs": 1,
      "ir": 3,
      "irs": 1,
      "bf": 36,
      "outs": 25,
      "r": 3,
      "er": 3,
      "h": 6,
      "b1": 5,
      "b2": 1,
      "b3": 0,
      "hr": 0,
      "bb": 4,
      "ibb": 0,
      "so": 6,
      "so_looking": 2,
      "so_swinging": 4,
      "hbp": 0,
      "wp": 0,
      "bk": 0,
      "pk": 0,
      "pocs": 0,
      "pitches_thrown": 140,
      "balls_thrown": 49,
      "strikes_thrown": 91,
      "first_pitch_strikes": 24,
      "zone_pitches": 71,
      "o_zone_pitches": 69,
      "zone_swings": 48,
      "o_zone_swings": 21,
      "zone_contacts": 41,
      "o_zone_contacts": 16,
      "gb": 8,
      "ld": 10,
      "fb": 8,
      "ip": 8.333333333333334,
      "cg": 0,
      "sho": 0,
      "qs": 0,
      "k_minus_bb": 2,
      "h9": 6.4799999999999995,
      "hr9": 0.0,
      "k9": 6.4799999999999995,
      "bb9": 4.319999999999999,
      "era": 3.2399999999999998,
      "whip": 1.2,
      "k_bb": 1.5,
      "fip": 3.2,
      "lob_pct": 0.7,
      "fps_pct": 0.6666666666666666,
      "zone_pct": 0.5071428571428571,
      "z_swing_pct": 0.676056338028169,
      "z_contact_pct": 0.8541666666666666,
      "ozone_pct": 0.4928571428571429,
      "ozone_swing_pct": 0.30434782608695654,
      "ozone_contact_pct": 0.7619047619047619,
      "swstr_pct": 0.08571428571428572,
      "so_looking_pct": 0.3333333333333333,
      "gb_pct": 0.3076923076923077,
      "ld_pct": 0.38461538461538464,
      "fb_pct": 0.3076923076923077,
      "gb_fb": 1.0,
      "ld_fb_ratio": 1.25,
      "po": 0,
      "a": 6,
      "e": 0,
      "dp": 0,
      "tp": 0,
      "pb": 0,
      "ci": 0,
      "cs": 0,
      "sba": 0,
      "tc": 6,
      "of_a": 0,
      "fpct": 1.0,
      "rf9": 0.6,
      "rfg": 0.6,
      "cs_pct": 0.0,
      "pb_g": 0.0
    },
    "P6631": {
      "g": 9,
      "gs": 0,
      "w": 0,
      "l": 2,
      "gf": 7,
      "sv": 5,
      "svo": 9,
      "hld": 0,
      "bs": 4,
      "ir": 0,
      "irs": 0,
      "bf": 43,
      "outs": 28,
      "r": 11,
      "er": 10,
      "h": 13,
      "b1": 7,
      "b2": 3,
      "b3": 0,
      "hr": 3,
      "bb": 2,
      "ibb": 0,
      "so": 11,
      "so_looking": 3,
      "so_swinging": 8,
      "hbp": 0,
      "wp": 0,
      "bk": 0,
      "pk": 0,
      "pocs": 0,
      "pitches_thrown": 166,
      "balls_thrown": 53,
      "strikes_thrown": 113,
      "first_pitch_strikes": 33,
      "zone_pitches": 91,
      "o_zone_pitches": 75,
      "zone_swings": 56,
      "o_zone_swings": 25,
      "zone_contacts": 53,
      "o_zone_contacts": 17,
      "gb": 12,
      "ld": 6,
      "fb": 12,
      "ip": 9.333333333333334,
      "cg": 0,
      "sho": 0,
      "qs": 0,
      "k_minus_bb": 9,
      "h9": 12.535714285714285,
      "hr9": 2.892857142857143,
      "k9": 10.607142857142856,
      "bb9": 1.9285714285714284,
      "era": 9.642857142857142,
      "whip": 1.607142857142857,
      "k_bb": 5.5,
      "fip": 5.664285714285715,
      "lob_pct": 0.37037037037037035,
      "fps_pct": 0.7674418604651163,
      "zone_pct": 0.5481927710843374,
      "z_swing_pct": 0.6153846153846154,
      "z_contact_pct": 0.9464285714285714,
      "ozone_pct": 0.45180722891566266,
      "ozone_swing_pct": 0.3333333333333333,
      "ozone_contact_pct": 0.68,
      "swstr_pct": 0.06626506024096386,
      "so_looking_pct": 0.2727272727272727,
      "gb_pct": 0.4,
      "ld_pct": 0.2,
      "fb_pct": 0.4,
      "gb_fb": 1.0,
      "ld_fb_ratio": 0.5,
      "po": 0,
      "a": 11,
      "e": 0,
      "dp": 0,
      "tp": 0,
      "pb": 0,
      "ci": 0,
      "cs": 0,
      "sba": 0,
      "tc": 11,
      "of_a": 0,
      "fpct": 1.0,
      "rf9": 1.2222222222222223,
      "rfg": 1.2222222222222223,
      "cs_pct": 0.0,
      "pb_g": 0.0
    }
  },
  "teams": {
    "SAN": {
      "w": 170,
      "g": 355,
      "r": 1372,
      "ra": 1436,
      "lob": 2432,
      "opp_pa": 13713,
      "opp_h": 2944,
      "opp_bb": 1158,
      "opp_so": 3188,
      "opp_hbp": 183,
      "opp_hr": 359,
      "opp_roe": 91,
      "der": 0.6560906515580737,
      "rpg": 3.8647887323943664,
      "rag": 4.045070422535211,
      "l": 185
    },
    "WAS": {
      "l": 181,
      "g": 355,
      "r": 1279,
      "ra": 1336,
      "lob": 2456,
      "opp_pa": 13455,
      "opp_h": 2777,
      "opp_bb": 1099,
      "opp_so": 3240,
      "opp_hbp": 171,
      "opp_hr": 339,
      "opp_roe": 87,
      "der": 0.6672089240065071,
      "rpg": 3.602816901408451,
      "rag": 3.7633802816901407,
      "w": 173
    }
  },
  "date": "2027-05-09"
}