{
  "players": {
    "P7399": {
      "g": 39,
      "gs": 39,
      "pa": 187,
      "ab": 171,
      "r": 29,
      "h": 56,
      "b1": 28,
      "b2": 11,
      "b3": 1,
      "hr": 16,
      "rbi": 29,
      "bb": 14,
      "ibb": 0,
      "hbp": 1,
      "so": 23,
      "so_looking": 10,
      "so_swinging": 13,
      "sh": 0,
      "sf": 1,
      "roe": 0,
      "fc": 5,
      "ci": 0,
      "gidp": 5,
      "sb": 5,
      "cs": 2,
      "po": 57,
      "pocs": 0,
      "pitches": 741,
      "lob": 34,
      "lead": 11,
      "gb": 66,
      "ld": 29,
      "fb": 54,
      "tb": 117,
      "xbh": 28,
      "p_pa": 3.962566844919786,
      "avg": 0.32748538011695905,
      "obp": 0.37967914438502676,
      "slg": 0.6842105263157895,
      "ops": 1.0638896707008163,
      "iso": 0.35672514619883045,
      "babip": 0.3007518796992481,
      "bb_pct": 0.0748663101604278,
      "k_pct": 0.12299465240641712,
      "bb_k": 0.6086956521739131,
      "so_looking_pct": 0.43478260869565216,
      "sb_pct": 0.7142857142857143,
      "gb_pct": 0.4429530201342282,
      "ld_pct": 0.19463087248322147,
      "fb_pct": 0.3624161073825503,
      "gb_fb": 1.2222222222222223,
      "ld_fb_ratio": 0.5370370370370371,
      "2b": 11,
      "3b": 1,
      "a": 136,
      "e": 2,
      "dp": 21,
      "tp": 0,
      "pk": 0,
      "pb": 0,
      "sba": 0,
      "tc": 195,
      "of_a": 0,
      "fpct": 0.9897435897435898,
      "rf9": 4.948717948717949,
      "rfg": 4.948717948717949,
      "cs_pct": 0.0,
      "pb_g": 0.0
    },
    "P9471": {
      "g": 39,
      "gs": 39,
      "pa": 182,
      "ab": 166,
      "r": 28,
      "h": 53,
      "b1": 28,
      "b2": 11,
      "b3": 1,
      "hr": 13,
      "rbi": 27,
      "bb": 9,
      "ibb": 0,
      "hbp": 5,
      "so": 29,
      "so_looking": 12,
      "so_swinging": 17,
      "sh": 0,
      "sf": 0,
      "roe": 1,
      "fc": 3,
      "ci": 0,
      "gidp": 2,
      "sb": 6,
      "cs": 0,
      "po": 108,
      "pocs": 0,
      "pitches": 679,
      "lob": 39,
      "lead": 24,
      "gb": 58,
      "ld": 34,
      "fb": 45,
      "tb": 105,
      "xbh": 25,
      "p_pa": 3.730769230769231,
      "avg": 0.3192771084337349,
      "obp": 0.37222222222222223,
      "slg": 0.6325301204819277,
      "ops": 1.0047523427041498,
      "iso": 0.3132530120481928,
      "babip": 0.3225806451612903,
      "bb_pct": 0.04945054945054945,
      "k_pct": 0.15934065934065933,
      "bb_k": 0.3103448275862069,
      "so_looking_pct": 0.41379310344827586,
      "sb_pct": 1.0,
      "gb_pct": 0.4233576642335766,
      "ld_pct": 0.24817518248175183,
      "fb_pct": 0.3284671532846715,
      "gb_fb": 1.288888888888889,
      "ld_fb_ratio": 0.7555555555555555,
      "2b": 11,
      "3b": 1,
      "a": 5,
      "e": 1,
      "dp": 0,
      "tp": 0,
      "pk": 0,
      "pb": 0,
      "sba": 0,
      "tc": 114,
      "of_a": 5,
      "fpct": 0.9912280701754386,
      "rf9": 2.8974358974358974,
      "rfg": 2.8974358974358974,
      "cs_pct": 0.0,
      "pb_g": 0.0
    },
    "P7050": {
      "g": 39,
      "gs": 39,
      "pa": 147,
      "ab": 124,
      "r": 18,
      "h": 30,
      "b1": 17,
      "b2": 7,
      "b3": 2,
      "hr": 4,
      "rbi": 14,
      "bb": 17,
      "ibb": 0,
      "hbp": 2,
      "so": 40,
      "so_looking": 16,
      "so_swinging": 24,
      "sh": 2,
      "sf": 2,
      "roe": 1,
      "fc": 1,
      "ci": 1,
      "gidp": 2,
      "sb": 3,
      "cs": 10,
      "po": 290,
      "pocs": 0,
      "pitches": 578,
      "lob": 28,
      "lead": 153,
      "gb": 31,
      "ld": 14,
      "fb": 40,
      "tb": 53,
      "xbh": 13,
      "p_pa": 3.931972789115646,
      "avg": 0.24193548387096775,
      "obp": 0.33793103448275863,
      "slg": 0.4274193548387097,
      "ops": 0.7653503893214684,
      "iso": 0.18548387096774194,
      "babip": 0.3170731707317073,
      "bb_pct": 0.11564625850340136,
      "k_pct": 0.272108843537415,
      "bb_k": 0.425,
      "so_looking_pct": 0.4,
      "sb_pct": 0.23076923076923078,
      "gb_pct": 0.36470588235294116,
      "ld_pct": 0.16470588235294117,
      "fb_pct": 0.47058823529411764,
      "gb_fb": 0.775,
      "ld_fb_ratio": 0.35,
      "2b": 7,
      "3b": 2,
      "a": 10,
      "e": 0,
      "dp": 0,
      "tp": 0,
      "pk": 0,
      "pb": 13,
      "sba": 65,
      "tc": 300,
      "of_a": 0,
      "fpct": 1.0,
      "rf9": 7.6923076923076925,
      "rfg": 7.6923076923076925,
      "cs_pct": 0.15384615384615385,
      "pb_g": 0.3333333333333333
    },
    "P2684": {
      "g": 30,
      "gs": 0,
      "pa": 44,
      "ab": 38,
      "r": 4,
      "h": 11,
      "b1": 5,
      "b2": 4,
      "b3": 0,
      "hr": 2,
      "rbi": 3,
      "bb": 5,
      "ibb": 0,
      "hbp": 1,
      "so": 15,
      "so_looking": 7,
      "so_swinging": 8,
      "sh": 0,
      "sf": 0,
      "roe": 0,
      "fc": 0,
      "ci": 0,
      "gidp": 0,
      "sb": 2,
      "cs": 1,
      "po": 25,
      "pocs": 0,
      "pitches": 181,
      "lob": 2,
      "lead": 0,
      "gb": 5,
      "ld": 4,
      "fb": 14,
      "tb": 21,
      "xbh": 6,
      "p_pa": 4.113636363636363,
      "avg": 0.2894736842105263,
      "obp": 0.38636363636363635,
      "slg": 0.5526315789473685,
      "ops": 0.9389952153110048,
      "iso": 0.26315789473684215,
      "babip": 0.42857142857142855,
      "bb_pct": 0.11363636363636363,
      "k_pct": 0.3409090909090909,
      "bb_k": 0.3333333333333333,
      "so_looking_pct": 0.4666666666666667,
      "sb_pct": 0.6666666666666666,
      "gb_pct": 0.21739130434782608,
      "ld_pct": 0.17391304347826086,
      "fb_pct": 0.6086956521739131,
      "gb_fb": 0.35714285714285715,
      "ld_fb_ratio": 0.2857142857142857,
      "2b": 4,
      "3b": 0,
      "a": 4,
      "e": 0,
      "dp": 2,
      "tp": 0,
      "pk": 0,
      "pb": 1,
      "sba": 3,
      "tc": 29,
      "of_a": 4,
      "fpct": 1.0,
      "rf9": 0.9666666666666667,
      "rfg": 0.9666666666666667,
      "cs_pct": 0.3333333333333333,
      "pb_g": 0.03333333333333333
    },
    "P3864": {
      "g": 39,
      "gs": 39,
      "pa": 148,
      "ab": 132,
      "r": 10,
      "h": 29,
      "b1": 20,
      "b2": 7,
      "b3": 1,
      "hr": 1,
      "rbi": 13,
      "bb": 14,
      "ibb": 0,
      "hbp": 0,
      "so": 37,
      "so_looking": 10,
      "so_swinging": 27,
      "sh": 0,
      "sf": 2,
      "roe": 1,
      "fc": 4,
      "ci": 0,
      "gidp": 2,
      "sb": 13,
      "cs": 1,
      "po": 0,
      "pocs": 0,
      "pitches": 573,
      "lob": 32,
      "lead": 150,
      "gb": 45,
      "ld": 25,
      "fb": 27,
      "tb": 41,
      "xbh": 9,
      "p_pa": 3.8716216216216215,
      "avg": 0.2196969696969697,
      "obp": 0.2905405405405405,
      "slg": 0.3106060606060606,
      "ops": 0.6011466011466011,
      "iso": 0.09090909090909091,
      "babip": 0.2916666666666667,
      "bb_pct": 0.0945945945945946,
      "k_pct": 0.25,
      "bb_k": 0.3783783783783784,
      "so_looking_pct": 0.2702702702702703,
      "sb_pct": 0.9285714285714286,
      "gb_pct": 0.4639175257731959,
      "ld_pct": 0.25773195876288657,
      "fb_pct": 0.27835051546391754,
      "gb_fb": 1.6666666666666667,
      "ld_fb_ratio": 0.9259259259259259,
      "2b": 7,
      "3b": 1
    },
    "P7192": {
      "g": 39,
      "gs": 39,
      "pa": 172,
      "ab": 155,
      "r": 19,
      "h": 45,
      "b1": 30,
      "b2": 10,
      "b3": 0,
      "hr": 5,
      "rbi": 18,
      "bb": 15,
      "ibb": 0,
      "hbp": 0,
      "so": 33,
      "so_looking": 5,
      "so_swinging": 28,
      "sh": 1,
      "sf": 1,
      "roe": 1,
      "fc": 2,
      "ci": 0,
      "gidp": 0,
      "sb": 6,
      "cs": 0,
      "po": 95,
      "pocs": 0,
      "pitches": 705,
      "lob": 34,
      "lead": 9,
      "gb": 53,
      "ld": 24,
      "fb": 46,
      "tb": 70,
      "xbh": 15,
      "p_pa": 4.098837209302325,
      "avg": 0.2903225806451613,
      "obp": 0.3508771929824561,
      "slg": 0.45161290322580644,
      "ops": 0.8024900962082626,
      "iso": 0.16129032258064513,
      "babip": 0.3389830508474576,
      "bb_pct": 0.0872093023255814,
      "k_pct": 0.19186046511627908,
      "bb_k": 0.45454545454545453,
      "so_looking_pct": 0.15151515151515152,
      "sb_pct": 1.0,
      "gb_pct": 0.43089430894308944,
      "ld_pct": 0.1951219512195122,
      "fb_pct": 0.37398373983739835,
      "gb_fb": 1.1521739130434783,
      "ld_fb_ratio": 0.5217391304347826,
      "2b": 10,
      "3b": 0,
      "a": 3,
      "e": 0,
      "dp": 0,
      "tp": 0,
      "pk": 0,
      "pb": 0,
      "sba": 0,
      "tc": 98,
      "of_a": 3,
      "fpct": 1.0,
      "rf9": 2.5128205128205128,
      "rfg": 2.5128205128205128,
      "cs_pct": 0.0,
      "pb_g": 0.0
    },
    "P3106": {
      "g": 39,
      "gs": 39,
      "pa": 167,
      "ab": 156,
      "r": 20,
      "h": 48,
      "b1": 29,
      "b2": 10,
      "b3": 0,
      "hr": 9,
      "rbi": 26,
      "bb": 9,
      "ibb": 0,
      "hbp": 0,
      "so": 27,
      "so_looking": 10,
      "so_swinging": 17,
      "sh": 1,
      "sf": 1,
      "roe": 3,
      "fc": 3,
      "ci": 0,
      "gidp": 4,
      "sb": 3,
      "cs": 2,
      "po": 7,
      "pocs": 0,
      "pitches": 615,
      "lob": 33,
      "lead": 16,
      "gb": 59,
      "ld": 31,
      "fb": 39,
      "tb": 85,
      "xbh": 19,
      "p_pa": 3.682634730538922,
      "avg": 0.3076923076923077,
      "obp": 0.3433734939759036,
      "slg": 0.5448717948717948,
      "ops": 0.8882452888476984,
      "iso": 0.23717948717948711,
      "babip": 0.32231404958677684,
      "bb_pct": 0.05389221556886228,
      "k_pct": 0.16167664670658682,
      "bb_k": 0.3333333333333333,
      "so_looking_pct": 0.37037037037037035,
      "sb_pct": 0.6,
      "gb_pct": 0.4573643410852713,
      "ld_pct": 0.24031007751937986,
      "fb_pct": 0.3023255813953488,
      "gb_fb": 1.5128205128205128,
      "ld_fb_ratio": 0.7948717948717948,
      "2b": 10,
      "3b": 0,
      "a": 37,
      "e": 0,
      "dp": 4,
      "tp": 0,
      "pk": 0,
      "pb": 0,
      "sba": 0,
      "tc": 44,
      "of_a": 0,
      "fpct": 1.0,
      "rf9": 1.1282051282051282,
      "rfg": 1.1282051282051282,
      "cs_pct": 0.0,
      "pb_g": 0.0
    },
    "P3610": {
      "g": 39,
      "gs": 39,
      "pa": 143,
      "ab": 128,
      "r": 14,
      "h": 28,
      "b1": 21,
      "b2": 6,
      "b3": 0,
      "hr": 1,
      "rbi": 6,
      "bb": 12,
      "ibb": 0,
      "hbp": 0,
      "so": 46,
      "so_looking": 12,
      "so_swinging": 34,
      "sh": 0,
      "sf": 1,
      "roe": 1,
      "fc": 2,
      "ci": 1,
      "gidp": 1,
      "sb": 7,
      "cs": 2,
      "po": 318,
      "pocs": 0,
      "pitches": 545,
      "lob": 22,
      "lead": 11,
      "gb": 34,
      "ld": 22,
      "fb": 27,
      "tb": 37,
      "xbh": 7,
      "p_pa": 3.8111888111888113,
      "avg": 0.21875,
      "obp": 0.28368794326241137,
      "slg": 0.2890625,
      "ops": 0.5727504432624113,
      "iso": 0.0703125,
      "babip": 0.32926829268292684,
      "bb_pct": 0.08391608391608392,
      "k_pct": 0.32167832167832167,
      "bb_k": 0.2608695652173913,
      "so_looking_pct": 0.2608695652173913,
      "sb_pct": 0.7777777777777778,
      "gb_pct": 0.40963855421686746,
      "ld_pct": 0.26506024096385544,
      "fb_pct": 0.3253012048192771,
      "gb_fb": 1.2592592592592593,
      "ld_fb_ratio": 0.8148148148148148,
      "2b": 6,
      "3b": 0,
      "a": 1,
      "e": 1,
      "dp": 23,
      "tp": 0,
      "pk": 0,
      "pb": 0,
      "sba": 0,
      "tc": 320,
      "of_a": 0,
      "fpct": 0.996875,
      "rf9": 8.179487179487179,
      "rfg": 8.179487179487179,
      "cs_pct": 0.0,
      "pb_g": 0.0
    },
    "P9328": {
      "g": 39,
      "gs": 39,
      "pa": 153,
      "ab": 133,
      "r": 12,
      "h": 30,
      "b1": 19,
      "b2": 5,
      "b3": 0,
      "hr": 6,
      "rbi": 21,
      "bb": 14,
      "ibb": 0,
      "hbp": 2,
      "so": 32,
      "so_looking": 5,
      "so_swinging": 27,
      "sh": 1,
      "sf": 2,
      "roe": 2,
      "fc": 3,
      "ci": 0,
      "gidp": 4,
      "sb": 3,
      "cs": 1,
      "po": 99,
      "pocs": 0,
      "pitches": 552,
      "lob": 26,
      "lead": 8,
      "gb": 48,
      "ld": 19,
      "fb": 35,
      "tb": 53,
      "xbh": 11,
      "p_pa": 3.607843137254902,
      "avg": 0.22556390977443608,
      "obp": 0.304635761589404,
      "slg": 0.39849624060150374,
      "ops": 0.7031320021909078,
      "iso": 0.17293233082706766,
      "babip": 0.24742268041237114,
      "bb_pct": 0.0915032679738562,
      "k_pct": 0.20915032679738563,
      "bb_k": 0.4375,
      "so_looking_pct": 0.15625,
      "sb_pct": 0.75,
      "gb_pct": 0.47058823529411764,
      "ld_pct": 0.18627450980392157,
      "fb_pct": 0.3431372549019608,
      "gb_fb": 1.3714285714285714,
      "ld_fb_ratio": 0.5428571428571428,
      "2b": 5,
      "3b": 0,
      "a": 4,
      "e": 2,
      "dp": 0,
      "tp": 0,
      "pk": 0,
      "pb": 0,
      "sba": 0,
      "tc": 105,
      "of_a": 4,
      "fpct": 0.9809523809523809,
      "rf9": 2.641025641025641,
      "rfg": 2.641025641025641,
      "cs_pct": 0.0,
      "pb_g": 0.0
    },
    "P9811": {
      "g": 39,
      "gs": 39,
      "pa": 138,
      "ab": 124,
      "r": 14,
      "h": 28,
      "b1": 19,
      "b2": 6,
      "b3": 1,
      "hr": 2,
      "rbi": 11,
      "bb": 9,
      "ibb": 0,
      "hbp": 2,
      "so": 47,
      "so_looking": 10,
      "so_swinging": 37,
      "sh": 0,
      "sf": 3,
      "roe": 1,
      "fc": 4,
      "ci": 0,
      "gidp": 1,
      "sb": 12,
      "cs": 0,
      "po": 21,
      "pocs": 0,
      "pitches": 530,
      "lob": 25,
      "lead": 141,
      "gb": 32,
      "ld": 16,
      "fb": 32,
      "tb": 42,
      "xbh": 9,
      "p_pa": 3.8405797101449277,
      "avg": 0.22580645161290322,
      "obp": 0.2826086956521739,
      "slg": 0.3387096774193548,
      "ops": 0.6213183730715287,
      "iso": 0.1129032258064516,
      "babip": 0.3333333333333333,
      "bb_pct": 0.06521739130434782,
      "k_pct": 0.34057971014492755,
      "bb_k": 0.19148936170212766,
      "so_looking_pct": 0.2127659574468085,
      "sb_pct": 1.0,
      "gb_pct": 0.4,
      "ld_pct": 0.2,
      "fb_pct": 0.4,
      "gb_fb": 1.0,
      "ld_fb_ratio": 0.5,
      "2b": 6,
      "3b": 1,
      "a": 131,
      "e": 2,
      "dp": 16,
      "tp": 0,
      "pk": 0,
      "pb": 0,
      "sba": 0,
      "tc": 154,
      "of_a": 0,
      "fpct": 0.987012987012987,
      "rf9": 3.8974358974358974,
      "rfg": 3.8974358974358974,
      "cs_pct": 0.0,
      "pb_g": 0.0
    },
    "P9310": {
      "g": 39,
      "gs": 39,
      "pa": 174,
      "ab": 151,
      "r": 17,
      "h": 21,
      "b1": 13,
      "b2": 4,
      "b3": 1,
      "hr": 3,
      "rbi": 11,
      "bb": 18,
      "ibb": 0,
      "hbp": 5,
      "so": 45,
      "so_looking": 10,
      "so_swinging": 35,
      "sh": 0,
      "sf": 0,
      "roe": 2,
      "fc": 1,
      "ci": 0,
      "gidp": 1,
      "sb": 12,
      "cs": 2,
      "po": 36,
      "pocs": 0,
      "pitches": 726,
      "lob": 23,
      "lead": 225,
      "gb": 37,
      "ld": 18,
      "fb": 51,
      "tb": 36,
      "xbh": 8,
      "p_pa": 4.172413793103448,
      "avg": 0.1390728476821192,
      "obp": 0.25287356321839083,
      "slg": 0.23841059602649006,
      "ops": 0.4912841592448809,
      "iso": 0.09933774834437087,
      "babip": 0.17475728155339806,
      "bb_pct": 0.10344827586206896,
      "k_pct": 0.25862068965517243,
      "bb_k": 0.4,
      "so_looking_pct": 0.2222222222222222,
      "sb_pct": 0.8571428571428571,
      "gb_pct": 0.3490566037735849,
      "ld_pct": 0.16981132075471697,
      "fb_pct": 0.4811320754716981,
      "gb_fb": 0.7254901960784313,
      "ld_fb_ratio": 0.35294117647058826,
      "2b": 4,
      "3b": 1,
      "a": 155,
      "e": 4,
      "dp": 22,
      "tp": 0,
      "pk": 0,
      "pb": 0,
      "sba": 0,
      "tc": 195,
      "of_a": 0,
      "fpct": 0.9794871794871794,
      "rf9": 4.897435897435898,
      "rfg": 4.897435897435898,
      "cs_pct": 0.0,
      "pb_g": 0.0
    },
    "P2377": {
      "g": 39,
      "gs": 39,
      "pa": 171,
      "ab": 156,
      "r": 19,
      "h": 33,
      "b1": 20,
      "b2": 7,
      "b3": 1,
      "hr": 5,
      "rbi": 11,
      "bb": 12,
      "ibb": 0,
      "hbp": 0,
      "so": 51,
      "so_looking": 16,
      "so_swinging": 35,
      "sh": 1,
      "sf": 1,
      "roe": 1,
      "fc": 2,
      "ci": 0,
      "gidp": 4,
      "sb": 8,
      "cs": 1,
      "po": 0,
      "pocs": 0,
      "pitches": 669,
      "lob": 27,
      "lead": 171,
      "gb": 45,
      "ld": 16,
      "fb": 45,
      "tb": 57,
      "xbh": 13,
      "p_pa": 3.912280701754386,
      "avg": 0.21153846153846154,
      "obp": 0.26627218934911245,
      "slg": 0.36538461538461536,
      "ops": 0.6316568047337279,
      "iso": 0.15384615384615383,
      "babip": 0.27722772277227725,
      "bb_pct": 0.07017543859649122,
      "k_pct": 0.2982456140350877,
      "bb_k": 0.23529411764705882,
      "so_looking_pct": 0.3137254901960784,
      "sb_pct": 0.8888888888888888,
      "gb_pct": 0.42452830188679247,
      "ld_pct": 0.1509433962264151,
      "fb_pct": 0.42452830188679247,
      "gb_fb": 1.0,
      "ld_fb_ratio": 0.35555555555555557,
      "2b": 7,
      "3b": 1
    },
    "P7879": {
      "g": 39,
      "gs": 39,
      "pa": 153,
      "ab": 134,
      "r": 15,
      "h": 38,
      "b1": 25,
      "b2": 9,
      "b3": 0,
      "hr": 4,
      "rbi": 14,
      "bb": 15,
      "ibb": 0,
      "hbp": 2,
      "so": 33,
      "so_looking": 7,
      "so_swinging": 26,
      "sh": 0,
      "sf": 2,
      "roe": 0,
      "fc": 2,
      "ci": 3,
      "gidp": 0,
      "sb": 10,
      "cs": 7,
      "po": 305,
      "pocs": 0,
      "pitches": 617,
      "lob": 36,
      "lead": 198,
      "gb": 42,
      "ld": 26,
      "fb": 35,
      "tb": 59,
      "xbh": 13,
      "p_pa": 4.032679738562091,
      "avg": 0.2835820895522388,
      "obp": 0.35947712418300654,
      "slg": 0.44029850746268656,
      "ops": 0.7997756316456931,
      "iso": 0.15671641791044777,
      "babip": 0.3434343434343434,
      "bb_pct": 0.09803921568627451,
      "k_pct": 0.21568627450980393,
      "bb_k": 0.45454545454545453,
      "so_looking_pct": 0.21212121212121213,
      "sb_pct": 0.5882352941176471,
      "gb_pct": 0.4077669902912621,
      "ld_pct": 0.2524271844660194,
      "fb_pct": 0.33980582524271846,
      "gb_fb": 1.2,
      "ld_fb_ratio": 0.7428571428571429,
      "2b": 9,
      "3b": 0,
      "a": 6,
      "e": 0,
      "dp": 0,
      "tp": 0,
      "pk": 0,
      "pb": 17,
      "sba": 85,
      "tc": 311,
      "of_a": 0,
      "fpct": 1.0,
      "rf9": 7.9743589743589745,
      "rfg": 7.9743589743589745,
      "cs_pct": 0.08235294117647059,
      "pb_g": 0.4358974358974359
    },
    "P9205": {
      "g": 31,
      "gs": 0,
      "pa": 15,
      "ab": 12,
      "r": 12,
      "h": 3,
      "b1": 2,
      "b2": 1,
      "b3": 0,
      "hr": 0,
      "rbi": 1,
      "bb": 2,
      "ibb": 0,
      "hbp": 1,
      "so": 1,
      "so_looking": 0,
      "so_swinging": 1,
      "sh": 0,
      "sf": 0,
      "roe": 0,
      "fc": 0,
      "ci": 0,
      "gidp": 0,
      "sb": 13,
      "cs": 1,
      "po": 14,
      "pocs": 0,
      "pitches": 49,
      "lob": 22,
      "lead": 172,
      "gb": 4,
      "ld": 3,
      "fb": 4,
      "tb": 4,
      "xbh": 1,
      "p_pa": 3.2666666666666666,
      "avg": 0.25,
      "obp": 0.4,
      "slg": 0.3333333333333333,
      "ops": 0.7333333333333334,
      "iso": 0.08333333333333331,
      "babip": 0.2727272727272727,
      "bb_pct": 0.13333333333333333,
      "k_pct": 0.06666666666666667,
      "bb_k": 2.0,
      "so_looking_pct": 0.0,
      "sb_pct": 0.9285714285714286,
      "gb_pct": 0.36363636363636365,
      "ld_pct": 0.2727272727272727,
      "fb_pct": 0.36363636363636365,
      "gb_fb": 1.0,
      "ld_fb_ratio": 0.75,
      "2b": 1,
      "3b": 0,
      "a": 2,
      "e": 0,
      "dp": 1,
      "tp": 0,
      "pk": 0,
      "pb": 0,
      "sba": 0,
      "tc": 16,
      "of_a": 0,
      "fpct": 1.0,
      "rf9": 0.5161290322580645,
      "rfg": 0.5161290322580645,
      "cs_pct": 0.0,
      "pb_g": 0.0
    },
    "P5528": {
      "g": 39,
      "gs": 39,
      "pa": 156,
      "ab": 143,
      "r": 15,
      "h": 39,
      "b1": 25,
      "b2": 8,
      "b3": 0,
      "hr": 6,
      "rbi": 15,
      "bb": 10,
      "ibb": 0,
      "hbp": 2,
      "so": 44,
      "so_looking": 11,
      "so_swinging": 33,
      "sh": 0,
      "sf": 0,
      "roe": 0,
      "fc": 0,
      "ci": 0,
      "gidp": 4,
      "sb": 4,
      "cs": 1,
      "po": 97,
      "pocs": 0,
      "pitches": 605,
      "lob": 19,
      "lead": 12,
      "gb": 46,
      "ld": 25,
      "fb": 28,
      "tb": 65,
      "xbh": 14,
      "p_pa": 3.878205128205128,
      "avg": 0.2727272727272727,
      "obp": 0.32903225806451614,
      "slg": 0.45454545454545453,
      "ops": 0.7835777126099707,
      "iso": 0.18181818181818182,
      "babip": 0.3548387096774194,
      "bb_pct": 0.0641025641025641,
      "k_pct": 0.28205128205128205,
      "bb_k": 0.22727272727272727,
      "so_looking_pct": 0.25,
      "sb_pct": 0.8,
      "gb_pct": 0.46464646464646464,
      "ld_pct": 0.25252525252525254,
      "fb_pct": 0.2828282828282828,
      "gb_fb": 1.6428571428571428,
      "ld_fb_ratio": 0.8928571428571429,
      "2b": 8,
      "3b": 0,
      "a": 2,
      "e": 1,
      "dp": 0,
      "tp": 0,
      "pk": 0,
      "pb": 0,
      "sba": 0,
      "tc": 100,
      "of_a": 2,
      "fpct": 0.99,
      "rf9": 2.5384615384615383,
      "rfg": 2.5384615384615383,
      "cs_pct": 0.0,
      "pb_g": 0.0
    },
    "P4999": {
      "g": 39,
      "gs": 39,
      "pa": 156,
      "ab": 142,
      "r": 7,
      "h": 28,
      "b1": 20,
      "b2": 8,
      "b3": 0,
      "hr": 0,
      "rbi": 8,
      "bb": 10,
      "ibb": 0,
      "hbp": 3,
      "so": 51,
      "so_looking": 4,
      "so_swinging": 47,
      "sh": 0,
      "sf": 1,
      "roe": 1,
      "fc": 2,
      "ci": 0,
      "gidp": 3,
      "sb": 6,
      "cs": 0,
      "po": 38,
      "pocs": 0,
      "pitches": 610,
      "lob": 22,
      "lead": 11,
      "gb": 35,
      "ld": 20,
      "fb": 37,
      "tb": 36,
      "xbh": 8,
      "p_pa": 3.91025641025641,
      "avg": 0.19718309859154928,
      "obp": 0.26282051282051283,
      "slg": 0.2535211267605634,
      "ops": 0.5163416395810763,
      "iso": 0.05633802816901409,
      "babip": 0.30434782608695654,
      "bb_pct": 0.0641025641025641,
      "k_pct": 0.3269230769230769,
      "bb_k": 0.19607843137254902,
      "so_looking_pct": 0.0784313725490196,
      "sb_pct": 1.0,
      "gb_pct": 0.3804347826086957,
      "ld_pct": 0.21739130434782608,
      "fb_pct": 0.40217391304347827,
      "gb_fb": 0.9459459459459459,
      "ld_fb_ratio": 0.5405405405405406,
      "2b": 8,
      "3b": 0,
      "a": 127,
      "e": 1,
      "dp": 21,
      "tp": 0,
      "pk": 0,
      "pb": 0,
      "sba": 0,
      "tc": 166,
      "of_a": 0,
      "fpct": 0.9939759036144579,
      "rf9": 4.230769230769231,
      "rfg": 4.230769230769231,
      "cs_pct": 0.0,
      "pb_g": 0.0
    },
    "P9597": {
      "g": 39,
      "gs": 39,
      "pa": 149,
      "ab": 123,
      "r": 13,
      "h": 33,
      "b1": 14,
      "b2": 13,
      "b3": 0,
      "hr": 6,
      "rbi": 19,
      "bb": 16,
      "ibb": 0,
      "hbp": 4,
      "so": 27,
      "so_looking": 5,
      "so_swinging": 22,
      "sh": 1,
      "sf": 4,
      "roe": 0,
      "fc": 3,
      "ci": 0,
      "gidp": 3,
      "sb": 6,
      "cs": 0,
      "po": 11,
      "pocs": 0,
      "pitches": 562,
      "lob": 38,
      "lead": 6,
      "gb": 40,
      "ld": 25,
      "fb": 35,
      "tb": 64,
      "xbh": 19,
      "p_pa": 3.771812080536913,
      "avg": 0.2682926829268293,
      "obp": 0.36054421768707484,
      "slg": 0.5203252032520326,
      "ops": 0.8808694209391075,
      "iso": 0.2520325203252033,
      "babip": 0.2872340425531915,
      "bb_pct": 0.10738255033557047,
      "k_pct": 0.18120805369127516,
      "bb_k": 0.5925925925925926,
      "so_looking_pct": 0.18518518518518517,
      "sb_pct": 1.0,
      "gb_pct": 0.4,
      "ld_pct": 0.25,
      "fb_pct": 0.35,
      "gb_fb": 1.1428571428571428,
      "ld_fb_ratio": 0.7142857142857143,
      "2b": 13,
      "3b": 0,
      "a": 24,
      "e": 0,
      "dp": 0,
      "tp": 0,
      "pk": 0,
      "pb": 0,
      "sba": 0,
      "tc": 35,
      "of_a": 0,
      "fpct": 1.0,
      "rf9": 0.8974358974358975,
      "rfg": 0.8974358974358975,
      "cs_pct": 0.0,
      "pb_g": 0.0
    },
    "P4137": {
      "g": 39,
      "gs": 39,
      "pa": 144,
      "ab": 124,
      "r": 8,
      "h": 24,
      "b1": 18,
      "b2": 3,
      "b3": 0,
      "hr": 3,
      "rbi": 10,
      "bb": 16,
      "ibb": 0,
      "hbp": 4,
      "so": 45,
      "so_looking": 9,
      "so_swinging": 36,
      "sh": 0,
      "sf": 0,
      "roe": 1,
      "fc": 1,
      "ci": 0,
      "gidp": 1,
      "sb": 5,
      "cs": 0,
      "po": 99,
      "pocs": 0,
      "pitches": 571,
      "lob": 29,
      "lead": 11,
      "gb": 31,
      "ld": 16,
      "fb": 31,
      "tb": 36,
      "xbh": 6,
      "p_pa": 3.9652777777777777,
      "avg": 0.1935483870967742,
      "obp": 0.3055555555555556,
      "slg": 0.2903225806451613,
      "ops": 0.5958781362007168,
      "iso": 0.09677419354838712,
      "babip": 0.27631578947368424,
      "bb_pct": 0.1111111111111111,
      "k_pct": 0.3125,
      "bb_k": 0.35555555555555557,
      "so_looking_pct": 0.2,
      "sb_pct": 1.0,
      "gb_pct": 0.3974358974358974,
      "ld_pct": 0.20512820512820512,
      "fb_pct": 0.3974358974358974,
      "gb_fb": 1.0,
      "ld_fb_ratio": 0.5161290322580645,
      "2b": 3,
      "3b": 0,
      "a": 9,
      "e": 3,
      "dp": 0,
      "tp": 0,
      "pk": 0,
      "pb": 0,
      "sba": 0,
      "tc": 111,
      "of_a": 9,
      "fpct": 0.972972972972973,
      "rf9": 2.769230769230769,
      "rfg": 2.769230769230769,
      "cs_pct": 0.0,
      "pb_g": 0.0
    },
    "P9442": {
      "g": 33,
      "gs": 0,
      "pa": 47,
      "ab": 42,
      "r": 3,
      "h": 5,
      "b1": 4,
      "b2": 0,
      "b3": 0,
      "hr": 1,
      "rbi": 3,
      "bb": 4,
      "ibb": 0,
      "hbp": 1,
      "so": 18,
      "so_looking": 4,
      "so_swinging": 14,
      "sh": 0,
      "sf": 0,
      "roe": 0,
      "fc": 0,
      "ci": 0,
      "gidp": 0,
      "sb": 2,
      "cs": 0,
      "po": 27,
      "pocs": 0,
      "pitches": 195,
      "lob": 5,
      "lead": 4,
      "gb": 11,
      "ld": 6,
      "fb": 7,
      "tb": 8,
      "xbh": 1,
      "p_pa": 4.148936170212766,
      "avg": 0.11904761904761904,
      "obp": 0.2127659574468085,
      "slg": 0.19047619047619047,
      "ops": 0.40324214792299895,
      "iso": 0.07142857142857142,
      "babip": 0.17391304347826086,
      "bb_pct": 0.0851063829787234,
      "k_pct": 0.3829787234042553,
      "bb_k": 0.2222222222222222,
      "so_looking_pct": 0.2222222222222222,
      "sb_pct": 1.0,
      "gb_pct": 0.4583333333333333,
      "ld_pct": 0.25,
      "fb_pct": 0.2916666666666667,
      "gb_fb": 1.5714285714285714,
      "ld_fb_ratio": 0.8571428571428571,
      "2b": 0,
      "3b": 0,
      "a": 0,
      "e": 0,
      "dp": 0,
      "tp": 0,
      "pk": 0,
      "pb": 0,
      "sba": 3,
      "tc": 27,
      "of_a": 0,
      "fpct": 1.0,
      "rf9": 0.8181818181818182,
      "rfg": 0.8181818181818182,
      "cs_pct": 0.0,
      "pb_g": 0.0
    },
    "P4601": {
      "g": 39,
      "gs": 39,
      "pa": 160,
      "ab": 145,
      "r": 10,
      "h": 29,
      "b1": 18,
      "b2": 7,
      "b3": 1,
      "hr": 3,
      "rbi": 19,
      "bb": 11,
      "ibb": 0,
      "hbp": 0,
      "so": 39,
      "so_looking": 10,
      "so_swinging": 29,
      "sh": 0,
      "sf": 2,
      "roe": 1,
      "fc": 1,
      "ci": 0,
      "gidp": 4,
      "sb": 2,
      "cs": 0,
      "po": 298,
      "pocs": 0,
      "pitches": 639,
      "lob": 18,
      "lead": 11,
      "gb": 47,
      "ld": 23,
      "fb": 38,
      "tb": 47,
      "xbh": 11,
      "p_pa": 3.99375,
      "avg": 0.2,
      "obp": 0.25316455696202533,
      "slg": 0.32413793103448274,
      "ops": 0.5773024879965081,
      "iso": 0.12413793103448273,
      "babip": 0.24761904761904763,
      "bb_pct": 0.06875,
      "k_pct": 0.24375,
      "bb_k": 0.28205128205128205,
      "so_looking_pct": 0.2564102564102564,
      "sb_pct": 1.0,
      "gb_pct": 0.4351851851851852,
      "ld_pct": 0.21296296296296297,
      "fb_pct": 0.35185185185185186,
      "gb_fb": 1.236842105263158,
      "ld_fb_ratio": 0.6052631578947368,
      "2b": 7,
      "3b": 1,
      "a": 2,
      "e": 0,
      "dp": 22,
      "tp": 0,
      "pk": 0,
      "pb": 0,
      "sba": 0,
      "tc": 300,
      "of_a": 0,
      "fpct": 1.0,
      "rf9": 7.6923076923076925,
      "rfg": 7.6923076923076925,
      "cs_pct": 0.0,
      "pb_g": 0.0
    },
    "P4213": {
      "g": 39,
      "gs": 39,
      "pa": 107,
      "ab": 100,
      "r": 4,
      "h": 17,
      "b1": 13,
      "b2": 3,
      "b3": 0,
      "hr": 1,
      "rbi": 6,
      "bb": 6,
      "ibb": 0,
      "hbp": 1,
      "so": 37,
      "so_looking": 6,
      "so_swinging": 31,
      "sh": 0,
      "sf": 0,
      "roe": 1,
      "fc": 2,
      "ci": 0,
      "gidp": 3,
      "sb": 3,
      "cs": 0,
      "po": 90,
      "pocs": 0,
      "pitches": 398,
      "lob": 21,
      "lead": 9,
      "gb": 22,
      "ld": 11,
      "fb": 30,
      "tb": 23,
      "xbh": 4,
      "p_pa": 3.7196261682242993,
      "avg": 0.17,
      "obp": 0.22429906542056074,
      "slg": 0.23,
      "ops": 0.45429906542056075,
      "iso": 0.06,
      "babip": 0.25806451612903225,
      "bb_pct": 0.056074766355140186,
      "k_pct": 0.34579439252336447,
      "bb_k": 0.16216216216216217,
      "so_looking_pct": 0.16216216216216217,
      "sb_pct": 1.0,
      "gb_pct": 0.3492063492063492,
      "ld_pct": 0.1746031746031746,
      "fb_pct": 0.47619047619047616,
      "gb_fb": 0.7333333333333333,
      "ld_fb_ratio": 0.36666666666666664,
      "2b": 3,
      "3b": 0,
      "a": 4,
      "e": 0,
      "dp": 0,
      "tp": 0,
      "pk": 0,
      "pb": 0,
      "sba": 0,
      "tc": 94,
      "of_a": 4,
      "fpct": 1.0,
      "rf9": 2.41025641025641,
      "rfg": 2.41025641025641,
      "cs_pct": 0.0,
      "pb_g": 0.0
    },
    "P6559": {
      "g": 8,
      "gs": 8,
      "w": 3,
      "l": 1,
      "gf": 0,
      "sv": 0,
      "svo": 0,
      "hld": 0,
      "bs": 0,
      "ir": 0,
      "irs": 0,
      "bf": 196,
      "outs": 146,
      "r": 14,
      "er": 13,
      "h": 34,
      "b1": 26,
      "b2": 5,
      "b3": 1,
      "hr": 2,
      "bb": 18,
      "ibb": 0,
      "so": 47,
      "so_looking": 9,
      "so_swinging": 38,
      "hbp": 1,
      "wp": 0,
      "bk": 0,
      "pk": 0,
      "pocs": 0,
      "pitches_thrown": 769,
      "balls_thrown": 275,
      "strikes_thrown": 494,
      "first_pitch_strikes": 130,
      "zone_pitches": 383,
      "o_zone_pitches": 386,
      "zone_swings": 246,
      "o_zone_swings": 119,
      "zone_contacts": 209,
      "o_zone_contacts": 70,
      "gb": 63,
      "ld": 23,
      "fb": 42,
      "ip": 48.666666666666664,
      "cg": 0,
      "sho": 0,
      "qs": 0,
      "k_minus_bb": 29,
      "h9": 6.287671232876713,
      "hr9": 0.36986301369863017,
      "k9": 8.691780821917808,
      "bb9": 3.328767123287671,
      "era": 2.404109589041096,
      "whip": 1.0684931506849316,
      "k_bb": 2.611111111111111,
      "fip": 2.9739726027397264,
      "lob_pct": 0.7768924302788844,
      "fps_pct": 0.6632653061224489,
      "zone_pct": 0.4980494148244473,
      "z_swing_pct": 0.6422976501305483,
      "z_contact_pct": 0.8495934959349594,
      "ozone_pct": 0.5019505851755527,
      "ozone_swing_pct": 0.3082901554404145,
      "ozone_contact_pct": 0.5882352941176471,
      "swstr_pct": 0.11183355006501951,
      "so_looking_pct": 0.19148936170212766,
      "gb_pct": 0.4921875,
      "ld_pct": 0.1796875,
      "fb_pct": 0.328125,
      "gb_fb": 1.5,
      "ld_fb_ratio": 0.5476190476190477,
      "po": 0,
      "a": 45,
      "e": 0,
      "dp": 0,
      "tp": 0,
      "pb": 0,
      "ci": 0,
      "cs": 0,
      "sba": 0,
      "tc": 45,
      "of_a": 0,
      "fpct": 1.0,
      "rf9": 5.625,
      "rfg": 5.625,
      "cs_pct": 0.0,
      "pb_g": 0.0
    },
    "P8361": {
      "g": 11,
      "gs": 0,
      "w": 0,
      "l": 0,
      "gf": 5,
      "sv": 5,
      "svo": 11,
      "hld": 5,
      "bs": 1,
      "ir": 2,
      "irs": 0,
      "bf": 45,
      "outs": 31,
      "r": 2,
      "er": 2,
      "h": 8,
      "b1": 3,
      "b2": 4,
      "b3": 0,
      "hr": 1,
      "bb": 4,
      "ibb": 0,
      "so": 6,
      "so_looking": 1,
      "so_swinging": 5,
      "hbp": 1,
      "wp": 2,
      "bk": 0,
      "pk": 0,
      "pocs": 0,
      "pitches_thrown": 171,
      "balls_thrown": 57,
      "strikes_thrown": 114,
      "first_pitch_strikes": 32,
      "zone_pitches": 83,
      "o_zone_pitches": 88,
      "zone_swings": 53,
      "o_zone_swings": 35,
      "zone_contacts": 47,
      "o_zone_contacts": 27,
      "gb": 13,
      "ld": 10,
      "fb": 10,
      "ip": 10.333333333333334,
      "cg": 0,
      "sho": 0,
      "qs": 0,
      "k_minus_bb": 2,
      "h9": 6.967741935483871,
      "hr9": 0.8709677419354839,
      "k9": 5.225806451612903,
      "bb9": 3.4838709677419355,
      "era": 1.7419354838709677,
      "whip": 1.161290322580645,
      "k_bb": 1.5,
      "fip": 4.748387096774193,
      "lob_pct": 0.9482758620689655,
      "fps_pct": 0.7111111111111111,
      "zone_pct": 0.4853801169590643,
      "z_swing_pct": 0.6385542168674698,
      "z_contact_pct": 0.8867924528301887,
      "ozone_pct": 0.5146198830409356,
      "ozone_swing_pct": 0.3977272727272727,
      "ozone_contact_pct": 0.7714285714285715,
      "swstr_pct": 0.08187134502923976,
      "so_looking_pct": 0.16666666666666666,
      "gb_pct": 0.3939393939393939,
      "ld_pct": 0.30303030303030304,
      "fb_pct": 0.30303030303030304,
      "gb_fb": 1.3,
      "ld_fb_ratio": 1.0,
      "po": 0,
      "a": 4,
      "e": 0,
      "dp": 0,
      "tp": 0,
      "pb": 0,
      "ci": 0,
      "cs": 0,
      "sba": 0,
      "tc": 4,
      "of_a": 0,
      "fpct": 1.0,
      "rf9": 0.36363636363636365,
      "rfg": 0.36363636363636365,
      "cs_pct": 0.0,
      "pb_g": 0.0
    },
    "P7115": {
      "g": 17,
      "gs": 0,
      "w": 2,
      "l": 0,
      "gf": 2,
      "sv": 0,
      "svo": 7,
      "hld": 7,
      "bs": 0,
      "ir": 19,
      "irs": 4,
      "bf": 88,
      "outs": 63,
      "r": 3,
      "er": 3,
      "h": 19,
      "b1": 14,
      "b2": 4,
      "b3": 0,
      "hr": 1,
      "bb": 9,
      "ibb": 0,
      "so": 18,
      "so_looking": 3,
      "so_swinging": 15,
      "hbp": 1,
      "wp": 0,
      "bk": 0,
      "pk": 0,
      "pocs": 0,
      "pitches_thrown": 340,
      "balls_thrown": 127,
      "strikes_thrown": 213,
      "first_pitch_strikes": 43,
      "zone_pitches": 170,
      "o_zone_pitches": 170,
      "zone_swings": 93,
      "o_zone_swings": 51,
      "zone_contacts": 81,
      "o_zone_contacts": 37,
      "gb": 29,
      "ld": 11,
      "fb": 19,
      "ip": 21.0,
      "cg": 0,
      "sho": 0,
      "qs": 0,
      "k_minus_bb": 9,
      "h9": 8.142857142857142,
      "hr9": 0.42857142857142855,
      "k9": 7.714285714285714,
      "bb9": 3.857142857142857,
      "era": 1.2857142857142858,
      "whip": 1.3333333333333333,
      "k_bb": 2.0,
      "fip": 3.5333333333333337,
      "lob_pct": 0.9420289855072463,
      "fps_pct": 0.48863636363636365,
      "zone_pct": 0.5,
      "z_swing_pct": 0.5470588235294118,
      "z_contact_pct": 0.8709677419354839,
      "ozone_pct": 0.5,
      "ozone_swing_pct": 0.3,
      "ozone_contact_pct": 0.7254901960784313,
      "swstr_pct": 0.07647058823529412,
      "so_looking_pct": 0.16666666666666666,
      "gb_pct": 0.4915254237288136,
      "ld_pct": 0.1864406779661017,
      "fb_pct": 0.3220338983050847,
      "gb_fb": 1.5263157894736843,
      "ld_fb_ratio": 0.5789473684210527,
      "po": 0,
      "a": 18,
      "e": 0,
      "dp": 0,
      "tp": 0,
      "pb": 0,
      "ci": 0,
      "cs": 0,
      "sba": 0,
      "tc": 18,
      "of_a": 0,
      "fpct": 1.0,
      "rf9": 1.0588235294117647,
      "rfg": 1.0588235294117647,
      "cs_pct": 0.0,
      "pb_g": 0.0
    },
    "P8067": {
      "g": 8,
      "gs": 8,
      "w": 0,
      "l": 5,
      "gf": 0,
      "sv": 0,
      "svo": 0,
      "hld": 0,
      "bs": 0,
      "ir": 0,
      "irs": 0,
      "bf": 190,
      "outs": 130,
      "r": 18,
      "er": 17,
      "h": 44,
      "b1": 26,
      "b2": 12,
      "b3": 1,
      "hr": 5,
      "bb": 14,
      "ibb": 0,
      "so": 39,
      "so_looking": 13,
      "so_swinging": 26,
      "hbp": 3,
      "wp": 4,
      "bk": 0,
      "pk": 0,
      "pocs": 0,
      "pitches_thrown": 712,
      "balls_thrown": 240,
      "strikes_thrown": 472,
      "first_pitch_strikes": 112,
      "zone_pitches": 370,
      "o_zone_pitches": 342,
      "zone_swings": 247,
      "o_zone_swings": 107,
      "zone_contacts": 212,
      "o_zone_contacts": 78,
      "gb": 47,
      "ld": 27,
      "fb": 53,
      "ip": 43.333333333333336,
      "cg": 0,
      "sho": 0,
      "qs": 0,
      "k_minus_bb": 25,
      "h9": 9.138461538461538,
      "hr9": 1.0384615384615383,
      "k9": 8.1,
      "bb9": 2.9076923076923076,
      "era": 3.5307692307692307,
      "whip": 1.3384615384615384,
      "k_bb": 2.7857142857142856,
      "fip": 4.076923076923077,
      "lob_pct": 0.7962962962962963,
      "fps_pct": 0.5894736842105263,
      "zone_pct": 0.5196629213483146,
      "z_swing_pct": 0.6675675675675675,
      "z_contact_pct": 0.8582995951417004,
      "ozone_pct": 0.4803370786516854,
      "ozone_swing_pct": 0.3128654970760234,
      "ozone_contact_pct": 0.7289719626168224,
      "swstr_pct": 0.0898876404494382,
      "so_looking_pct": 0.3333333333333333,
      "gb_pct": 0.3700787401574803,
      "ld_pct": 0.2125984251968504,
      "fb_pct": 0.41732283464566927,
      "gb_fb": 0.8867924528301887,
      "ld_fb_ratio": 0.5094339622641509,
      "po": 0,
      "a": 36,
      "e": 0,
      "dp": 0,
      "tp": 0,
      "pb": 0,
      "ci": 0,
      "cs": 0,
      "sba": 0,
      "tc": 36,
      "of_a": 0,
      "fpct": 1.0,
      "rf9": 4.5,
      "rfg": 4.5,
      "cs_pct": 0.0,
      "pb_g": 0.0
    },
    "P2417": {
      "g": 14,
      "gs": 0,
      "w": 0,
      "l": 0,
      "gf": 2,
      "sv": 0,
      "svo": 3,
      "hld": 3,
      "bs": 0,
      "ir": 4,
      "irs": 2,
      "bf": 56,
      "outs": 40,
      "r": 1,
      "er": 1,
      "h": 10,
      "b1": 7,
      "b2": 2,
      "b3": 1,
      "hr": 0,
      "bb": 3,
      "ibb": 0,
      "so": 13,
      "so_looking": 4,
      "so_swinging": 9,
      "hbp": 4,
      "wp": 0,
      "bk": 0,
      "pk": 0,
      "pocs": 0,
      "pitches_thrown": 205,
      "balls_thrown": 57,
      "strikes_thrown": 148,
      "first_pitch_strikes": 40,
      "zone_pitches": 108,
      "o_zone_pitches": 97,
      "zone_swings": 58,
      "o_zone_swings": 43,
      "zone_contacts": 48,
      "o_zone_contacts": 28,
      "gb": 15,
      "ld": 6,
      "fb": 15,
      "ip": 13.333333333333334,
      "cg": 0,
      "sho": 0,
      "qs": 0,
      "k_minus_bb": 10,
      "h9": 6.75,
      "hr9": 0.0,
      "k9": 8.775,
      "bb9": 2.025,
      "era": 0.6749999999999999,
      "whip": 0.975,
      "k_bb": 4.333333333333333,
      "fip": 2.825,
      "lob_pct": 0.9411764705882353,
      "fps_pct": 0.7142857142857143,
      "zone_pct": 0.526829268292683,
      "z_swing_pct": 0.5370370370370371,
      "z_contact_pct": 0.8275862068965517,
      "ozone_pct": 0.47317073170731705,
      "ozone_swing_pct": 0.44329896907216493,
      "ozone_contact_pct": 0.6511627906976745,
      "swstr_pct": 0.12195121951219512,
      "so_looking_pct": 0.3076923076923077,
      "gb_pct": 0.4166666666666667,
      "ld_pct": 0.16666666666666666,
      "fb_pct": 0.4166666666666667,
      "gb_fb": 1.0,
      "ld_fb_ratio": 0.4,
      "po": 0,
      "a": 12,
      "e": 0,
      "dp": 0,
      "tp": 0,
      "pb": 0,
      "ci": 0,
      "cs": 0,
      "sba": 0,
      "tc": 12,
      "of_a": 0,
      "fpct": 1.0,
      "rf9": 0.8571428571428571,
      "rfg": 0.8571428571428571,
      "cs_pct": 0.0,
      "pb_g": 0.0
    },
    "P8416": {
      "g": 13,
      "gs": 0,
      "w": 1,
      "l": 2,
      "gf": 10,
      "sv": 1,
      "svo": 4,
      "hld": 0,
      "bs": 3,
      "ir": 10,
      "irs": 1,
      "bf": 107,
      "outs": 71,
      "r": 21,
      "er": 17,
      "h": 24,
      "b1": 12,
      "b2": 4,
      "b3": 0,
      "hr": 8,
      "bb": 10,
      "ibb": 0,
      "so": 18,
      "so_looking": 4,
      "so_swinging": 14,
      "hbp": 1,
      "wp": 0,
      "bk": 0,
      "pk": 0,
      "pocs": 0,
      "pitches_thrown": 403,
      "balls_thrown": 147,
      "strikes_thrown": 256,
      "first_pitch_strikes": 61,
      "zone_pitches": 202,
      "o_zone_pitches": 201,
      "zone_swings": 138,
      "o_zone_swings": 55,
      "zone_contacts": 123,
      "o_zone_contacts": 37,
      "gb": 32,
      "ld": 16,
      "fb": 29,
      "ip": 23.666666666666668,
      "cg": 0,
      "sho": 0,
      "qs": 0,
      "k_minus_bb": 8,
      "h9": 9.126760563380282,
      "hr9": 3.0422535211267605,
      "k9": 6.845070422535211,
      "bb9": 3.8028169014084505,
      "era": 6.464788732394366,
      "whip": 1.436619718309859,
      "k_bb": 1.8,
      "fip": 7.467605633802817,
      "lob_pct": 0.5882352941176471,
      "fps_pct": 0.5700934579439252,
      "zone_pct": 0.5012406947890818,
      "z_swing_pct": 0.6831683168316832,
      "z_contact_pct": 0.8913043478260869,
      "ozone_pct": 0.4987593052109181,
      "ozone_swing_pct": 0.2736318407960199,
      "ozone_contact_pct": 0.6727272727272727,
      "swstr_pct": 0.08188585607940446,
      "so_looking_pct": 0.2222222222222222,
      "gb_pct": 0.4155844155844156,
      "ld_pct": 0.2077922077922078,
      "fb_pct": 0.37662337662337664,
      "gb_fb": 1.103448275862069,
      "ld_fb_ratio": 0.5517241379310345,
      "po": 0,
      "a": 17,
      "e": 0,
      "dp": 0,
      "tp": 0,
      "pb": 0,
      "ci": 0,
      "cs": 0,
      "sba": 0,
      "tc": 17,
      "of_a": 0,
      "fpct": 1.0,
      "rf9": 1.3076923076923077,
      "rfg": 1.3076923076923077,
      "cs_pct": 0.0,
      "pb_g": 0.0
    }
  },
  "teams": {
    "SAN1": {
      "l": 395,
      "g": 687,
      "r": 2218,
      "ra": 2640,
      "lob": 4817,
      "opp_pa": 26048,
      "opp_h": 5401,
      "opp_bb": 2189,
      "opp_so": 5925,
      "opp_hbp": 310,
      "opp_hr": 704,
      "opp_roe": 160,
      "der": 0.6713356973995273,
      "rpg": 3.2285298398835516,
      "rag": 3.8427947598253276,
      "w": 291
    },
    "PHO": {
      "l": 313,
      "g": 687,
      "r": 2982,
      "ra": 2729,
      "lob": 4931,
      "opp_pa": 26444,
      "opp_h": 5607,
      "opp_bb": 2293,
      "opp_so": 6046,
      "opp_hbp": 356,
      "opp_hr": 693,
      "opp_roe": 156,
      "der": 0.6621130393996248,
      "rpg": 4.3406113537117905,
      "rag": 3.972343522561863,
      "w": 374
    }
  },
  "date": "2029-05-19"
}